Workbook
Name Slicer_City: #N/A
Name Slicer_Month: #N/A

Sheet Pivot
A3: Category | B3: Sum of Net Revenue | D3: City | E3: Sum of Net Revenue | G3: Month | H3: Sum of Net Revenue
A4: Electronics | B4: 179205.2 | D4: Bengaluru | E4: 62297.481 | G4: Apr-2026 | H4: 72152.268
A5: Fashion | B5: 74673.846 | D5: Bhubaneswar | E5: 40778.362 | G5: Feb-2026 | H5: 69670.656
A6: Food & Beverage | B6: 22663.751 | D6: Chennai | E6: 38687.255 | G6: Jan-2026 | H6: 40682.241
A7: Grocery | B7: 31986.249 | D7: Delhi | E7: 43207.195 | G7: Jun-2026 | H7: 54727.284
A8: Home & Living | B8: 56806.626 | D8: Hyderabad | E8: 47101.951 | G8: Mar-2026 | H8: 81661.369
A9: Pharmacy | B9: 17339.38 | D9: Kolkata | E9: 25854.54 | G9: May-2026 | H9: 63781.235
A10: Grand Total | B10: 382675.05 | D10: Mumbai | E10: 51737.585 | G10: Grand Total | H10: 382675.05
D11: Pune | E11: 73010.685
D12: Grand Total | E12: 382675.05
A15: Payment Method | B15: Sum of Net Revenue | D15: Month | E15: Total Profit | F15: Total Loss | H15: Delivery Status | I15: Sum of Net Revenue | J15: Count of Order ID
A16: Cash on Delivery | B16: 110397.12 | D16: Apr-2026 | E16: 14454.47 | F16: 1332.6186 | H16: Cancelled | I16: 0 | J16: 12
A17: Credit/Debit Card | B17: 98127.144 | D17: Feb-2026 | E17: 15949.249 | F17: 2522.8721 | H17: Delivered | I17: 382264.05 | J17: 192
A18: Net Banking | B18: 74884.815 | D18: Jan-2026 | E18: 10237.418 | F18: 4344.5773 | H18: Returned | I18: 411 | J18: 16
A19: UPI/Wallet | B19: 99265.979 | D19: Jun-2026 | E19: 10522.553 | F19: 14136.774 | H19: Grand Total | I19: 382675.05 | J19: 220
A20: Grand Total | B20: 382675.05 | D20: Mar-2026 | E20: 12522.484 | F20: 3182.2317
D21: May-2026 | E21: 13475.931 | F21: 9123.1602
D22: Grand Total | E22: 77162.105 | F22: 34642.234
A25: Sum of Net Revenue | B25: Sum of Net Profit | C25: Count of Orders | D25: Average of Delivery Time | E25: Average of Rating
A26: 382675.05 | B26: 42519.871 | C26: 220 | D26: 56.524038 | E26: 3.9038462
A50: Category | B50: Revenue | D50: City | E50: Revenue | G50: Month | H50: Revenue | J50: Payment Method | K50: Revenue | M50: Month | N50: Total Profit | O50: Total Loss
A51: =Pivot!$A$4 -> Electronics | B51: =Pivot!$B$4 -> 179205.2 | D51: =Pivot!$D$4 -> Bengaluru | E51: =Pivot!$E$4 -> 62297.481 | G51: =Pivot!$G$4 -> Apr-2026 | H51: =Pivot!$H$4 -> 72152.268 | J51: =Pivot!$A$16 -> Cash on Delivery | K51: =Pivot!$B$16 -> 110397.12 | M51: =Pivot!$D$16 -> Apr-2026 | N51: =Pivot!$E$16 -> 14454.47 | O51: =Pivot!$F$16 -> 1332.6186
A52: =Pivot!$A$5 -> Fashion | B52: =Pivot!$B$5 -> 74673.846 | D52: =Pivot!$D$5 -> Bhubaneswar | E52: =Pivot!$E$5 -> 40778.362 | G52: =Pivot!$G$5 -> Feb-2026 | H52: =Pivot!$H$5 -> 69670.656 | J52: =Pivot!$A$17 -> Credit/Debit Card | K52: =Pivot!$B$17 -> 98127.144 | M52: =Pivot!$D$17 -> Feb-2026 | N52: =Pivot!$E$17 -> 15949.249 | O52: =Pivot!$F$17 -> 2522.8721
A53: =Pivot!$A$6 -> Food & Beverage | B53: =Pivot!$B$6 -> 22663.751 | D53: =Pivot!$D$6 -> Chennai | E53: =Pivot!$E$6 -> 38687.255 | G53: =Pivot!$G$6 -> Jan-2026 | H53: =Pivot!$H$6 -> 40682.241 | J53: =Pivot!$A$18 -> Net Banking | K53: =Pivot!$B$18 -> 74884.815 | M53: =Pivot!$D$18 -> Jan-2026 | N53: =Pivot!$E$18 -> 10237.418 | O53: =Pivot!$F$18 -> 4344.5773
A54: =Pivot!$A$7 -> Grocery | B54: =Pivot!$B$7 -> 31986.249 | D54: =Pivot!$D$7 -> Delhi | E54: =Pivot!$E$7 -> 43207.195 | G54: =Pivot!$G$7 -> Jun-2026 | H54: =Pivot!$H$7 -> 54727.284 | J54: =Pivot!$A$19 -> UPI/Wallet | K54: =Pivot!$B$19 -> 99265.979 | M54: =Pivot!$D$19 -> Jun-2026 | N54: =Pivot!$E$19 -> 10522.553 | O54: =Pivot!$F$19 -> 14136.774
A55: =Pivot!$A$8 -> Home & Living | B55: =Pivot!$B$8 -> 56806.626 | D55: =Pivot!$D$8 -> Hyderabad | E55: =Pivot!$E$8 -> 47101.951 | G55: =Pivot!$G$8 -> Mar-2026 | H55: =Pivot!$H$8 -> 81661.369 | M55: =Pivot!$D$20 -> Mar-2026 | N55: =Pivot!$E$20 -> 12522.484 | O55: =Pivot!$F$20 -> 3182.2317
A56: =Pivot!$A$9 -> Pharmacy | B56: =Pivot!$B$9 -> 17339.38 | D56: =Pivot!$D$9 -> Kolkata | E56: =Pivot!$E$9 -> 25854.54 | G56: =Pivot!$G$9 -> May-2026 | H56: =Pivot!$H$9 -> 63781.235 | M56: =Pivot!$D$21 -> May-2026 | N56: =Pivot!$E$21 -> 13475.931 | O56: =Pivot!$F$21 -> 9123.1602
D57: =Pivot!$D$10 -> Mumbai | E57: =Pivot!$E$10 -> 51737.585
D58: =Pivot!$D$11 -> Pune | E58: =Pivot!$E$11 -> 73010.685

Sheet Riders (HR)
A1: Rider ID | B1: Name | C1: City | D1: Join Date | E1: Employment Status | F1: Monthly Base Pay ($) | G1: Total Orders Assigned | H1: Delivered Orders | I1: On-Time Deliveries (<=45 min) | J1: On-Time % | K1: Avg Customer Rating | L1: Avg Delivery Time (mins) | M1: Rank Key
A2: RD1001 | B2: Suresh Kumar | C2: Pune | D2: 45679 | E2: Active | F2: 16000 | G2: =COUNTIF(Orders!$M$2:$M$221,$B2) -> 6 | H2: =COUNTIFS(Orders!$M$2:$M$221,$B2,Orders!$N$2:$N$221,"Delivered") -> 6 | I2: =COUNTIFS(Orders!$M$2:$M$221,$B2,Orders!$N$2:$N$221,"Delivered",Orders!$O$2:$O$221,"<=45") -> 2 | J2: =IFERROR(I2/H2,0) -> 0.33333333 | K2: =IFERROR(AVERAGEIFS(Orders!$P$2:$P$221,Orders!$M$2:$M$221,$B2,Orders!$N$2:$N$221,"Delivered"),0) -> 4.3333333 | L2: =IFERROR(AVERAGEIFS(Orders!$O$2:$O$221,Orders!$M$2:$M$221,$B2,Orders!$N$2:$N$221,"Delivered"),0) -> 60.833333 | M2: =H2-ROW()/100000 -> 5.99998
A3: RD1002 | B3: Ramesh Yadav | C3: Hyderabad | D3: 45477 | E3: Active | F3: 14000 | G3: =COUNTIF(Orders!$M$2:$M$221,$B3) -> 14 | H3: =COUNTIFS(Orders!$M$2:$M$221,$B3,Orders!$N$2:$N$221,"Delivered") -> 13 | I3: =COUNTIFS(Orders!$M$2:$M$221,$B3,Orders!$N$2:$N$221,"Delivered",Orders!$O$2:$O$221,"<=45") -> 9 | J3: =IFERROR(I3/H3,0) -> 0.69230769 | K3: =IFERROR(AVERAGEIFS(Orders!$P$2:$P$221,Orders!$M$2:$M$221,$B3,Orders!$N$2:$N$221,"Delivered"),0) -> 4 | L3: =IFERROR(AVERAGEIFS(Orders!$O$2:$O$221,Orders!$M$2:$M$221,$B3,Orders!$N$2:$N$221,"Delivered"),0) -> 44.538462 | M3: =H3-ROW()/100000 -> 12.99997
A4: RD1003 | B4: Anita Behera | C4: Pune | D4: 45698 | E4: Active | F4: 14000 | G4: =COUNTIF(Orders!$M$2:$M$221,$B4) -> 5 | H4: =COUNTIFS(Orders!$M$2:$M$221,$B4,Orders!$N$2:$N$221,"Delivered") -> 5 | I4: =COUNTIFS(Orders!$M$2:$M$221,$B4,Orders!$N$2:$N$221,"Delivered",Orders!$O$2:$O$221,"<=45") -> 1 | J4: =IFERROR(I4/H4,0) -> 0.2 | K4: =IFERROR(AVERAGEIFS(Orders!$P$2:$P$221,Orders!$M$2:$M$221,$B4,Orders!$N$2:$N$221,"Delivered"),0) -> 4.2 | L4: =IFERROR(AVERAGEIFS(Orders!$O$2:$O$221,Orders!$M$2:$M$221,$B4,Orders!$N$2:$N$221,"Delivered"),0) -> 57 | M4: =H4-ROW()/100000 -> 4.99996
A5: RD1004 | B5: Bikash Mallick | C5: Pune | D5: 45367 | E5: Active | F5: 18000 | G5: =COUNTIF(Orders!$M$2:$M$221,$B5) -> 16 | H5: =COUNTIFS(Orders!$M$2:$M$221,$B5,Orders!$N$2:$N$221,"Delivered") -> 12 | I5: =COUNTIFS(Orders!$M$2:$M$221,$B5,Orders!$N$2:$N$221,"Delivered",Orders!$O$2:$O$221,"<=45") -> 8 | J5: =IFERROR(I5/H5,0) -> 0.66666667 | K5: =IFERROR(AVERAGEIFS(Orders!$P$2:$P$221,Orders!$M$2:$M$221,$B5,Orders!$N$2:$N$221,"Delivered"),0) -> 4.1666667 | L5: =IFERROR(AVERAGEIFS(Orders!$O$2:$O$221,Orders!$M$2:$M$221,$B5,Orders!$N$2:$N$221,"Delivered"),0) -> 45.416667 | M5: =H5-ROW()/100000 -> 11.99995
A6: RD1005 | B6: Deepak Sahu | C6: Bhubaneswar | D6: 45660 | E6: Active | F6: 18000 | G6: =COUNTIF(Orders!$M$2:$M$221,$B6) -> 10 | H6: =COUNTIFS(Orders!$M$2:$M$221,$B6,Orders!$N$2:$N$221,"Delivered") -> 10 | I6: =COUNTIFS(Orders!$M$2:$M$221,$B6,Orders!$N$2:$N$221,"Delivered",Orders!$O$2:$O$221,"<=45") -> 2 | J6: =IFERROR(I6/H6,0) -> 0.2 | K6: =IFERROR(AVERAGEIFS(Orders!$P$2:$P$221,Orders!$M$2:$M$221,$B6,Orders!$N$2:$N$221,"Delivered"),0) -> 3.8 | L6: =IFERROR(AVERAGEIFS(Orders!$O$2:$O$221,Orders!$M$2:$M$221,$B6,Orders!$N$2:$N$221,"Delivered"),0) -> 68.1 | M6: =H6-ROW()/100000 -> 9.99994
A7: RD1006 | B7: Farhan Ali | C7: Hyderabad | D7: 45566 | E7: Active | F7: 16000 | G7: =COUNTIF(Orders!$M$2:$M$221,$B7) -> 8 | H7: =COUNTIFS(Orders!$M$2:$M$221,$B7,Orders!$N$2:$N$221,"Delivered") -> 5 | I7: =COUNTIFS(Orders!$M$2:$M$221,$B7,Orders!$N$2:$N$221,"Delivered",Orders!$O$2:$O$221,"<=45") -> 2 | J7: =IFERROR(I7/H7,0) -> 0.4 | K7: =IFERROR(AVERAGEIFS(Orders!$P$2:$P$221,Orders!$M$2:$M$221,$B7,Orders!$N$2:$N$221,"Delivered"),0) -> 4.6 | L7: =IFERROR(AVERAGEIFS(Orders!$O$2:$O$221,Orders!$M$2:$M$221,$B7,Orders!$N$2:$N$221,"Delivered"),0) -> 50.8 | M7: =H7-ROW()/100000 -> 4.99993
A8: RD1007 | B8: Gaurav Nanda | C8: Bhubaneswar | D8: 45766 | E8: Active | F8: 15000 | G8: =COUNTIF(Orders!$M$2:$M$221,$B8) -> 9 | H8: =COUNTIFS(Orders!$M$2:$M$221,$B8,Orders!$N$2:$N$221,"Delivered") -> 6 | I8: =COUNTIFS(Orders!$M$2:$M$221,$B8,Orders!$N$2:$N$221,"Delivered",Orders!$O$2:$O$221,"<=45") -> 2 | J8: =IFERROR(I8/H8,0) -> 0.33333333 | K8: =IFERROR(AVERAGEIFS(Orders!$P$2:$P$221,Orders!$M$2:$M$221,$B8,Orders!$N$2:$N$221,"Delivered"),0) -> 4.3333333 | L8: =IFERROR(AVERAGEIFS(Orders!$O$2:$O$221,Orders!$M$2:$M$221,$B8,Orders!$N$2:$N$221,"Delivered"),0) -> 60.833333 | M8: =H8-ROW()/100000 -> 5.99992
A9: RD1008 | B9: Harpreet Singh | C9: Mumbai | D9: 45709 | E9: Active | F9: 15000 | G9: =COUNTIF(Orders!$M$2:$M$221,$B9) -> 14 | H9: =COUNTIFS(Orders!$M$2:$M$221,$B9,Orders!$N$2:$N$221,"Delivered") -> 13 | I9: =COUNTIFS(Orders!$M$2:$M$221,$B9,Orders!$N$2:$N$221,"Delivered",Orders!$O$2:$O$221,"<=45") -> 3 | J9: =IFERROR(I9/H9,0) -> 0.23076923 | K9: =IFERROR(AVERAGEIFS(Orders!$P$2:$P$221,Orders!$M$2:$M$221,$B9,Orders!$N$2:$N$221,"Delivered"),0) -> 3.8461538 | L9: =IFERROR(AVERAGEIFS(Orders!$O$2:$O$221,Orders!$M$2:$M$221,$B9,Orders!$N$2:$N$221,"Delivered"),0) -> 63.461538 | M9: =H9-ROW()/100000 -> 12.99991
A10: RD1009 | B10: Imran Khan | C10: Delhi | D10: 45462 | E10: Active | F10: 17000 | G10: =COUNTIF(Orders!$M$2:$M$221,$B10) -> 12 | H10: =COUNTIFS(Orders!$M$2:$M$221,$B10,Orders!$N$2:$N$221,"Delivered") -> 9 | I10: =COUNTIFS(Orders!$M$2:$M$221,$B10,Orders!$N$2:$N$221,"Delivered",Orders!$O$2:$O$221,"<=45") -> 3 | J10: =IFERROR(I10/H10,0) -> 0.33333333 | K10: =IFERROR(AVERAGEIFS(Orders!$P$2:$P$221,Orders!$M$2:$M$221,$B10,Orders!$N$2:$N$221,"Delivered"),0) -> 3.8888889 | L10: =IFERROR(AVERAGEIFS(Orders!$O$2:$O$221,Orders!$M$2:$M$221,$B10,Orders!$N$2:$N$221,"Delivered"),0) -> 53.222222 | M10: =H10-ROW()/100000 -> 8.9999
A11: RD1010 | B11: Jyoti Panda | C11: Delhi | D11: 45401 | E11: Active | F11: 18000 | G11: =COUNTIF(Orders!$M$2:$M$221,$B11) -> 18 | H11: =COUNTIFS(Orders!$M$2:$M$221,$B11,Orders!$N$2:$N$221,"Delivered") -> 16 | I11: =COUNTIFS(Orders!$M$2:$M$221,$B11,Orders!$N$2:$N$221,"Delivered",Orders!$O$2:$O$221,"<=45") -> 7 | J11: =IFERROR(I11/H11,0) -> 0.4375 | K11: =IFERROR(AVERAGEIFS(Orders!$P$2:$P$221,Orders!$M$2:$M$221,$B11,Orders!$N$2:$N$221,"Delivered"),0) -> 4.125 | L11: =IFERROR(AVERAGEIFS(Orders!$O$2:$O$221,Orders!$M$2:$M$221,$B11,Orders!$N$2:$N$221,"Delivered"),0) -> 52.0625 | M11: =H11-ROW()/100000 -> 15.99989
A12: RD1011 | B12: Kunal Mehta | C12: Bhubaneswar | D12: 45487 | E12: Active | F12: 18000 | G12: =COUNTIF(Orders!$M$2:$M$221,$B12) -> 15 | H12: =COUNTIFS(Orders!$M$2:$M$221,$B12,Orders!$N$2:$N$221,"Delivered") -> 13 | I12: =COUNTIFS(Orders!$M$2:$M$221,$B12,Orders!$N$2:$N$221,"Delivered",Orders!$O$2:$O$221,"<=45") -> 3 | J12: =IFERROR(I12/H12,0) -> 0.23076923 | K12: =IFERROR(AVERAGEIFS(Orders!$P$2:$P$221,Orders!$M$2:$M$221,$B12,Orders!$N$2:$N$221,"Delivered"),0) -> 3.9230769 | L12: =IFERROR(AVERAGEIFS(Orders!$O$2:$O$221,Orders!$M$2:$M$221,$B12,Orders!$N$2:$N$221,"Delivered"),0) -> 57.615385 | M12: =H12-ROW()/100000 -> 12.99988
A13: RD1012 | B13: Lalita Rout | C13: Mumbai | D13: 45415 | E13: Active | F13: 16000 | G13: =COUNTIF(Orders!$M$2:$M$221,$B13) -> 11 | H13: =COUNTIFS(Orders!$M$2:$M$221,$B13,Orders!$N$2:$N$221,"Delivered") -> 10 | I13: =COUNTIFS(Orders!$M$2:$M$221,$B13,Orders!$N$2:$N$221,"Delivered",Orders!$O$2:$O$221,"<=45") -> 1 | J13: =IFERROR(I13/H13,0) -> 0.1 | K13: =IFERROR(AVERAGEIFS(Orders!$P$2:$P$221,Orders!$M$2:$M$221,$B13,Orders!$N$2:$N$221,"Delivered"),0) -> 4.4 | L13: =IFERROR(AVERAGEIFS(Orders!$O$2:$O$221,Orders!$M$2:$M$221,$B13,Orders!$N$2:$N$221,"Delivered"),0) -> 66 | M13: =H13-ROW()/100000 -> 9.99987
... A21: RD1020 | B21: Usha Rani | C21: Hyderabad | D21: 45490 | E21: Active | F21: 14000 | G21: =COUNTIF(Orders!$M$2:$M$221,$B21) -> 7 | H21: =COUNTIFS(Orders!$M$2:$M$221,$B21,Orders!$N$2:$N$221,"Delivered") -> 7 | I21: =COUNTIFS(Orders!$M$2:$M$221,$B21,Orders!$N$2:$N$221,"Delivered",Orders!$O$2:$O$221,"<=45") -> 0 | J21: =IFERROR(I21/H21,0) -> 0 | K21: =IFERROR(AVERAGEIFS(Orders!$P$2:$P$221,Orders!$M$2:$M$221,$B21,Orders!$N$2:$N$221,"Delivered"),0) -> 3.8571429 | L21: =IFERROR(AVERAGEIFS(Orders!$O$2:$O$221,Orders!$M$2:$M$221,$B21,Orders!$N$2:$N$221,"Delivered"),0) -> 67.285714 | M21: =H21-ROW()/100000 -> 6.99979

Sheet Loss Analysis
B2: Loss Cause Analysis — supports the Dashboard's month-wise Profit/Loss table
B4: Loss Orders by Month and Cause
B5: Month | C5: Order Cancelled | D5: Order Returned | E5: High Discount | F5: Delivery Cost Exceeded Order Value | G5: Low Order Value / Thin Margin | H5: Total Loss Orders | I5: Most Common Cause | J5: Least Common Cause
B6: Jan-2026 | C6: =COUNTIFS(Orders!$Q$2:$Q$221,$B6,Orders!$Z$2:$Z$221,C$5) -> 3 | D6: =COUNTIFS(Orders!$Q$2:$Q$221,$B6,Orders!$Z$2:$Z$221,D$5) -> 3 | E6: =COUNTIFS(Orders!$Q$2:$Q$221,$B6,Orders!$Z$2:$Z$221,E$5) -> 1 | F6: =COUNTIFS(Orders!$Q$2:$Q$221,$B6,Orders!$Z$2:$Z$221,F$5) -> 0 | G6: =COUNTIFS(Orders!$Q$2:$Q$221,$B6,Orders!$Z$2:$Z$221,G$5) -> 0 | H6: =SUM(C6:G6) -> 7 | I6: =IF(H6=0,"No Losses",INDEX($C$5:$G$5,MATCH(MAX(C6:G6),C6:G6,0))) -> Order Cancelled | J6: =IF(H6=0,"No Losses",INDEX($C$5:$G$5,MATCH(MIN(N6:R6),N6:R6,0))) -> High Discount | N6: =IF(C6=0,99999,C6) -> 3 | O6: =IF(D6=0,99999,D6) -> 3 | P6: =IF(E6=0,99999,E6) -> 1 | Q6: =IF(F6=0,99999,F6) -> 99999 | R6: =IF(G6=0,99999,G6) -> 99999
B7: Feb-2026 | C7: =COUNTIFS(Orders!$Q$2:$Q$221,$B7,Orders!$Z$2:$Z$221,C$5) -> 3 | D7: =COUNTIFS(Orders!$Q$2:$Q$221,$B7,Orders!$Z$2:$Z$221,D$5) -> 2 | E7: =COUNTIFS(Orders!$Q$2:$Q$221,$B7,Orders!$Z$2:$Z$221,E$5) -> 2 | F7: =COUNTIFS(Orders!$Q$2:$Q$221,$B7,Orders!$Z$2:$Z$221,F$5) -> 0 | G7: =COUNTIFS(Orders!$Q$2:$Q$221,$B7,Orders!$Z$2:$Z$221,G$5) -> 0 | H7: =SUM(C7:G7) -> 7 | I7: =IF(H7=0,"No Losses",INDEX($C$5:$G$5,MATCH(MAX(C7:G7),C7:G7,0))) -> Order Cancelled | J7: =IF(H7=0,"No Losses",INDEX($C$5:$G$5,MATCH(MIN(N7:R7),N7:R7,0))) -> Order Returned | N7: =IF(C7=0,99999,C7) -> 3 | O7: =IF(D7=0,99999,D7) -> 2 | P7: =IF(E7=0,99999,E7) -> 2 | Q7: =IF(F7=0,99999,F7) -> 99999 | R7: =IF(G7=0,99999,G7) -> 99999
B8: Mar-2026 | C8: =COUNTIFS(Orders!$Q$2:$Q$221,$B8,Orders!$Z$2:$Z$221,C$5) -> 2 | D8: =COUNTIFS(Orders!$Q$2:$Q$221,$B8,Orders!$Z$2:$Z$221,D$5) -> 4 | E8: =COUNTIFS(Orders!$Q$2:$Q$221,$B8,Orders!$Z$2:$Z$221,E$5) -> 3 | F8: =COUNTIFS(Orders!$Q$2:$Q$221,$B8,Orders!$Z$2:$Z$221,F$5) -> 0 | G8: =COUNTIFS(Orders!$Q$2:$Q$221,$B8,Orders!$Z$2:$Z$221,G$5) -> 0 | H8: =SUM(C8:G8) -> 9 | I8: =IF(H8=0,"No Losses",INDEX($C$5:$G$5,MATCH(MAX(C8:G8),C8:G8,0))) -> Order Returned | J8: =IF(H8=0,"No Losses",INDEX($C$5:$G$5,MATCH(MIN(N8:R8),N8:R8,0))) -> Order Cancelled | N8: =IF(C8=0,99999,C8) -> 2 | O8: =IF(D8=0,99999,D8) -> 4 | P8: =IF(E8=0,99999,E8) -> 3 | Q8: =IF(F8=0,99999,F8) -> 99999 | R8: =IF(G8=0,99999,G8) -> 99999
B9: Apr-2026 | C9: =COUNTIFS(Orders!$Q$2:$Q$221,$B9,Orders!$Z$2:$Z$221,C$5) -> 3 | D9: =COUNTIFS(Orders!$Q$2:$Q$221,$B9,Orders!$Z$2:$Z$221,D$5) -> 2 | E9: =COUNTIFS(Orders!$Q$2:$Q$221,$B9,Orders!$Z$2:$Z$221,E$5) -> 2 | F9: =COUNTIFS(Orders!$Q$2:$Q$221,$B9,Orders!$Z$2:$Z$221,F$5) -> 0 | G9: =COUNTIFS(Orders!$Q$2:$Q$221,$B9,Orders!$Z$2:$Z$221,G$5) -> 0 | H9: =SUM(C9:G9) -> 7 | I9: =IF(H9=0,"No Losses",INDEX($C$5:$G$5,MATCH(MAX(C9:G9),C9:G9,0))) -> Order Cancelled | J9: =IF(H9=0,"No Losses",INDEX($C$5:$G$5,MATCH(MIN(N9:R9),N9:R9,0))) -> Order Returned | N9: =IF(C9=0,99999,C9) -> 3 | O9: =IF(D9=0,99999,D9) -> 2 | P9: =IF(E9=0,99999,E9) -> 2 | Q9: =IF(F9=0,99999,F9) -> 99999 | R9: =IF(G9=0,99999,G9) -> 99999
B10: May-2026 | C10: =COUNTIFS(Orders!$Q$2:$Q$221,$B10,Orders!$Z$2:$Z$221,C$5) -> 0 | D10: =COUNTIFS(Orders!$Q$2:$Q$221,$B10,Orders!$Z$2:$Z$221,D$5) -> 2 | E10: =COUNTIFS(Orders!$Q$2:$Q$221,$B10,Orders!$Z$2:$Z$221,E$5) -> 1 | F10: =COUNTIFS(Orders!$Q$2:$Q$221,$B10,Orders!$Z$2:$Z$221,F$5) -> 0 | G10: =COUNTIFS(Orders!$Q$2:$Q$221,$B10,Orders!$Z$2:$Z$221,G$5) -> 0 | H10: =SUM(C10:G10) -> 3 | I10: =IF(H10=0,"No Losses",INDEX($C$5:$G$5,MATCH(MAX(C10:G10),C10:G10,0))) -> Order Returned | J10: =IF(H10=0,"No Losses",INDEX($C$5:$G$5,MATCH(MIN(N10:R10),N10:R10,0))) -> High Discount | N10: =IF(C10=0,99999,C10) -> 99999 | O10: =IF(D10=0,99999,D10) -> 2 | P10: =IF(E10=0,99999,E10) -> 1 | Q10: =IF(F10=0,99999,F10) -> 99999 | R10: =IF(G10=0,99999,G10) -> 99999
B11: Jun-2026 | C11: =COUNTIFS(Orders!$Q$2:$Q$221,$B11,Orders!$Z$2:$Z$221,C$5) -> 1 | D11: =COUNTIFS(Orders!$Q$2:$Q$221,$B11,Orders!$Z$2:$Z$221,D$5) -> 3 | E11: =COUNTIFS(Orders!$Q$2:$Q$221,$B11,Orders!$Z$2:$Z$221,E$5) -> 1 | F11: =COUNTIFS(Orders!$Q$2:$Q$221,$B11,Orders!$Z$2:$Z$221,F$5) -> 0 | G11: =COUNTIFS(Orders!$Q$2:$Q$221,$B11,Orders!$Z$2:$Z$221,G$5) -> 0 | H11: =SUM(C11:G11) -> 5 | I11: =IF(H11=0,"No Losses",INDEX($C$5:$G$5,MATCH(MAX(C11:G11),C11:G11,0))) -> Order Returned | J11: =IF(H11=0,"No Losses",INDEX($C$5:$G$5,MATCH(MIN(N11:R11),N11:R11,0))) -> Order Cancelled | N11: =IF(C11=0,99999,C11) -> 1 | O11: =IF(D11=0,99999,D11) -> 3 | P11: =IF(E11=0,99999,E11) -> 1 | Q11: =IF(F11=0,99999,F11) -> 99999 | R11: =IF(G11=0,99999,G11) -> 99999
B12: Total | C12: =SUM(C6:C11) -> 12 | D12: =SUM(D6:D11) -> 16 | E12: =SUM(E6:E11) -> 10 | F12: =SUM(F6:F11) -> 0 | G12: =SUM(G6:G11) -> 0 | H12: =SUM(H6:H11) -> 38
B15: Total Loss Amount by Cause (All Months)
B16: Cause | C16: Number of Orders | D16: Total Loss ($) | E16: Avg Loss per Order ($)
B17: Order Cancelled | C17: =COUNTIF(Orders!$Z$2:$Z$221,B17) -> 12 | D17: =SUMIF(Orders!$Z$2:$Z$221,B17,Orders!$X$2:$X$221) -> 180 | E17: =IFERROR(D17/C17,0) -> 15
B18: Order Returned | C18: =COUNTIF(Orders!$Z$2:$Z$221,B18) -> 16 | D18: =SUMIF(Orders!$Z$2:$Z$221,B18,Orders!$X$2:$X$221) -> 31280.265 | E18: =IFERROR(D18/C18,0) -> 1955.0166
B19: High Discount | C19: =COUNTIF(Orders!$Z$2:$Z$221,B19) -> 10 | D19: =SUMIF(Orders!$Z$2:$Z$221,B19,Orders!$X$2:$X$221) -> 3181.9695 | E19: =IFERROR(D19/C19,0) -> 318.19695
B20: Delivery Cost Exceeded Order Value | C20: =COUNTIF(Orders!$Z$2:$Z$221,B20) -> 0 | D20: =SUMIF(Orders!$Z$2:$Z$221,B20,Orders!$X$2:$X$221) -> 0 | E20: =IFERROR(D20/C20,0) -> 0
B21: Low Order Value / Thin Margin | C21: =COUNTIF(Orders!$Z$2:$Z$221,B21) -> 0 | D21: =SUMIF(Orders!$Z$2:$Z$221,B21,Orders!$X$2:$X$221) -> 0 | E21: =IFERROR(D21/C21,0) -> 0
B22: Total | C22: =SUM(C17:C21) -> 38 | D22: =SUM(D17:D21) -> 34642.234

Sheet Dashboard
AF2: =IFERROR(GETPIVOTDATA("Sum of Net Revenue",Pivot!$A$25),0) -> 382675.05
AF3: =IFERROR(GETPIVOTDATA("Sum of Net Profit",Pivot!$A$25),0) -> 42519.871
AF4: =IFERROR(AF3/AF2,0) -> 0.11111221
AF5: =IFERROR(GETPIVOTDATA("Count of Orders",Pivot!$A$25),0) -> 220
AF6: =IFERROR(GETPIVOTDATA("Average of Delivery Time",Pivot!$A$25),0) -> 56.524038
AF7: =IFERROR(GETPIVOTDATA("Average of Rating",Pivot!$A$25),0) -> 3.9038462

Sheet Orders
A1: Order ID | B1: Order Date | C1: Customer Name | D1: City | E1: Channel | F1: Category | G1: Items | H1: Order Value ($) | I1: Discount % | J1: Delivery Charge ($) | K1: Net Revenue ($) | L1: Payment Method | M1: Delivery Partner | N1: Delivery Status | O1: Delivery Time (mins) | P1: Customer Rating (1-5) | Q1: Month | R1: Cost of Goods ($) | S1: Fulfillment Cost ($) | T1: Total Cost ($) | U1: Net Profit/(Loss) ($) | V1: Profit ($) | W1: Profit % | X1: Loss ($) | Y1: Loss % | Z1: Loss Cause
A2: ORD10206 | B2: 46024.935 | C2: Isha Das | D2: Hyderabad | E2: Mobile App | F2: Grocery | G2: 6 | H2: 1031.55 | I2: 0 | J2: 0 | K2: =IF(N2="Cancelled",0,IF(N2="Returned",J2,H2*(1-I2)+J2)) -> 1031.55 | L2: Cash on Delivery | M2: Jyoti Panda | N2: Delivered | O2: 66 | P2: 5 | Q2: =TEXT(tblOrders[[#This Row],[Order Date]],"mmm-yyyy") -> Jan-2026 | R2: =IF(N2="Cancelled",0,H2*INDEX(Assumptions!$C$7:$C$12,MATCH(F2,Assumptions!$B$7:$B$12,0))) -> 804.609 | S2: =IF(N2="Cancelled",Assumptions!$C$19,IF(N2="Returned",Assumptions!$C$17+O2*Assumptions!$C$18+Assumptions!$C$20,Assumptions!$C$17+O2*Assumptions!$C$18)) -> 44.8 | T2: =R2+S2 -> 849.409 | U2: =K2-T2 -> 182.141 | V2: =IF(U2>0,U2,0) -> 182.141 | W2: =IF(U2>0,U2/H2,0) -> 0.17657021 | X2: =IF(U2<0,-U2,0) -> 0 | Y2: =IF(U2<0,-U2/H2,0) -> 0 | Z2: =IF(U2>=0,"Profitable",IF(N2="Cancelled","Order Cancelled",IF(N2="Returned","Order Returned",IF(AND(I2>=0.15,U2<0),"High Discount",IF(S2>H2,"Delivery Cost Exceeded Order Value","Low Order Value / Thin Margin"))))) -> Profitable
A3: ORD10159 | B3: 46026.356 | C3: Sneha Das | D3: Chennai | E3: Mobile App | F3: Food & Beverage | G3: 3 | H3: 113.71 | I3: 0.2 | J3: 59 | K3: =IF(N3="Cancelled",0,IF(N3="Returned",J3,H3*(1-I3)+J3)) -> 149.968 | L3: Credit/Debit Card | M3: Deepak Sahu | N3: Delivered | O3: 30 | P3: 5 | Q3: =TEXT(tblOrders[[#This Row],[Order Date]],"mmm-yyyy") -> Jan-2026 | R3: =IF(N3="Cancelled",0,H3*INDEX(Assumptions!$C$7:$C$12,MATCH(F3,Assumptions!$B$7:$B$12,0))) -> 51.1695 | S3: =IF(N3="Cancelled",Assumptions!$C$19,IF(N3="Returned",Assumptions!$C$17+O3*Assumptions!$C$18+Assumptions!$C$20,Assumptions!$C$17+O3*Assumptions!$C$18)) -> 34 | T3: =R3+S3 -> 85.1695 | U3: =K3-T3 -> 64.7985 | V3: =IF(U3>0,U3,0) -> 64.7985 | W3: =IF(U3>0,U3/H3,0) -> 0.56985753 | X3: =IF(U3<0,-U3,0) -> 0 | Y3: =IF(U3<0,-U3/H3,0) -> 0 | Z3: =IF(U3>=0,"Profitable",IF(N3="Cancelled","Order Cancelled",IF(N3="Returned","Order Returned",IF(AND(I3>=0.15,U3<0),"High Discount",IF(S3>H3,"Delivery Cost Exceeded Order Value","Low Order Value / Thin Margin"))))) -> Profitable
A4: ORD10039 | B4: 46026.893 | C4: Riya Pillai | D4: Kolkata | E4: Mobile App | F4: Pharmacy | G4: 3 | H4: 982.53 | I4: 0.2 | J4: 59 | K4: =IF(N4="Cancelled",0,IF(N4="Returned",J4,H4*(1-I4)+J4)) -> 845.024 | L4: Credit/Debit Card | M4: Imran Khan | N4: Delivered | O4: 84 | P4: 5 | Q4: =TEXT(tblOrders[[#This Row],[Order Date]],"mmm-yyyy") -> Jan-2026 | R4: =IF(N4="Cancelled",0,H4*INDEX(Assumptions!$C$7:$C$12,MATCH(F4,Assumptions!$B$7:$B$12,0))) -> 687.771 | S4: =IF(N4="Cancelled",Assumptions!$C$19,IF(N4="Returned",Assumptions!$C$17+O4*Assumptions!$C$18+Assumptions!$C$20,Assumptions!$C$17+O4*Assumptions!$C$18)) -> 50.2 | T4: =R4+S4 -> 737.971 | U4: =K4-T4 -> 107.053 | V4: =IF(U4>0,U4,0) -> 107.053 | W4: =IF(U4>0,U4/H4,0) -> 0.10895647 | X4: =IF(U4<0,-U4,0) -> 0 | Y4: =IF(U4<0,-U4/H4,0) -> 0 | Z4: =IF(U4>=0,"Profitable",IF(N4="Cancelled","Order Cancelled",IF(N4="Returned","Order Returned",IF(AND(I4>=0.15,U4<0),"High Discount",IF(S4>H4,"Delivery Cost Exceeded Order Value","Low Order Value / Thin Margin"))))) -> Profitable
A5: ORD10167 | B5: 46029.39 | C5: Ishaan Iyer | D5: Bengaluru | E5: Mobile App | F5: Fashion | G5: 3 | H5: 3495.76 | I5: 0 | J5: 0 | K5: =IF(N5="Cancelled",0,IF(N5="Returned",J5,H5*(1-I5)+J5)) -> 3495.76 | L5: Cash on Delivery | M5: Sunil Barik | N5: Delivered | O5: 28 | P5: 5 | Q5: =TEXT(tblOrders[[#This Row],[Order Date]],"mmm-yyyy") -> Jan-2026 | R5: =IF(N5="Cancelled",0,H5*INDEX(Assumptions!$C$7:$C$12,MATCH(F5,Assumptions!$B$7:$B$12,0))) -> 1922.668 | S5: =IF(N5="Cancelled",Assumptions!$C$19,IF(N5="Returned",Assumptions!$C$17+O5*Assumptions!$C$18+Assumptions!$C$20,Assumptions!$C$17+O5*Assumptions!$C$18)) -> 33.4 | T5: =R5+S5 -> 1956.068 | U5: =K5-T5 -> 1539.692 | V5: =IF(U5>0,U5,0) -> 1539.692 | W5: =IF(U5>0,U5/H5,0) -> 0.44044557 | X5: =IF(U5<0,-U5,0) -> 0 | Y5: =IF(U5<0,-U5/H5,0) -> 0 | Z5: =IF(U5>=0,"Profitable",IF(N5="Cancelled","Order Cancelled",IF(N5="Returned","Order Returned",IF(AND(I5>=0.15,U5<0),"High Discount",IF(S5>H5,"Delivery Cost Exceeded Order Value","Low Order Value / Thin Margin"))))) -> Profitable
A6: ORD10041 | B6: 46030.662 | C6: Pooja Sharma | D6: Hyderabad | E6: Mobile App | F6: Electronics | G6: 3 | H6: 12129.22 | I6: 0 | J6: 0 | K6: =IF(N6="Cancelled",0,IF(N6="Returned",J6,H6*(1-I6)+J6)) -> 0 | L6: Cash on Delivery | M6: Imran Khan | N6: Cancelled | Q6: =TEXT(tblOrders[[#This Row],[Order Date]],"mmm-yyyy") -> Jan-2026 | R6: =IF(N6="Cancelled",0,H6*INDEX(Assumptions!$C$7:$C$12,MATCH(F6,Assumptions!$B$7:$B$12,0))) -> 0 | S6: =IF(N6="Cancelled",Assumptions!$C$19,IF(N6="Returned",Assumptions!$C$17+O6*Assumptions!$C$18+Assumptions!$C$20,Assumptions!$C$17+O6*Assumptions!$C$18)) -> 15 | T6: =R6+S6 -> 15 | U6: =K6-T6 -> -15 | V6: =IF(U6>0,U6,0) -> 0 | W6: =IF(U6>0,U6/H6,0) -> 0 | X6: =IF(U6<0,-U6,0) -> 15 | Y6: =IF(U6<0,-U6/H6,0) -> 0.001236683 | Z6: =IF(U6>=0,"Profitable",IF(N6="Cancelled","Order Cancelled",IF(N6="Returned","Order Returned",IF(AND(I6>=0.15,U6<0),"High Discount",IF(S6>H6,"Delivery Cost Exceeded Order Value","Low Order Value / Thin Margin"))))) -> Order Cancelled
A7: ORD10203 | B7: 46034.641 | C7: Arjun Patel | D7: Delhi | E7: Mobile App | F7: Electronics | G7: 1 | H7: 8650.68 | I7: 0.15 | J7: 0 | K7: =IF(N7="Cancelled",0,IF(N7="Returned",J7,H7*(1-I7)+J7)) -> 7353.078 | L7: Net Banking | M7: Kunal Mehta | N7: Delivered | O7: 49 | P7: 4 | Q7: =TEXT(tblOrders[[#This Row],[Order Date]],"mmm-yyyy") -> Jan-2026 | R7: =IF(N7="Cancelled",0,H7*INDEX(Assumptions!$C$7:$C$12,MATCH(F7,Assumptions!$B$7:$B$12,0))) -> 7612.5984 | S7: =IF(N7="Cancelled",Assumptions!$C$19,IF(N7="Returned",Assumptions!$C$17+O7*Assumptions!$C$18+Assumptions!$C$20,Assumptions!$C$17+O7*Assumptions!$C$18)) -> 39.7 | T7: =R7+S7 -> 7652.2984 | U7: =K7-T7 -> -299.2204 | V7: =IF(U7>0,U7,0) -> 0 | W7: =IF(U7>0,U7/H7,0) -> 0 | X7: =IF(U7<0,-U7,0) -> 299.2204 | Y7: =IF(U7<0,-U7/H7,0) -> 0.034589235 | Z7: =IF(U7>=0,"Profitable",IF(N7="Cancelled","Order Cancelled",IF(N7="Returned","Order Returned",IF(AND(I7>=0.15,U7<0),"High Discount",IF(S7>H7,"Delivery Cost Exceeded Order Value","Low Order Value / Thin Margin"))))) -> High Discount
A8: ORD10029 | B8: 46035.677 | C8: Divya Pillai | D8: Kolkata | E8: Mobile App | F8: Home & Living | G8: 2 | H8: 4848.22 | I8: 0.15 | J8: 0 | K8: =IF(N8="Cancelled",0,IF(N8="Returned",J8,H8*(1-I8)+J8)) -> 0 | L8: Cash on Delivery | M8: Rekha Sethi | N8: Returned | O8: 74 | P8: 3 | Q8: =TEXT(tblOrders[[#This Row],[Order Date]],"mmm-yyyy") -> Jan-2026 | R8: =IF(N8="Cancelled",0,H8*INDEX(Assumptions!$C$7:$C$12,MATCH(F8,Assumptions!$B$7:$B$12,0))) -> 3151.343 | S8: =IF(N8="Cancelled",Assumptions!$C$19,IF(N8="Returned",Assumptions!$C$17+O8*Assumptions!$C$18+Assumptions!$C$20,Assumptions!$C$17+O8*Assumptions!$C$18)) -> 67.2 | T8: =R8+S8 -> 3218.543 | U8: =K8-T8 -> -3218.543 | V8: =IF(U8>0,U8,0) -> 0 | W8: =IF(U8>0,U8/H8,0) -> 0 | X8: =IF(U8<0,-U8,0) -> 3218.543 | Y8: =IF(U8<0,-U8/H8,0) -> 0.66386076 | Z8: =IF(U8>=0,"Profitable",IF(N8="Cancelled","Order Cancelled",IF(N8="Returned","Order Returned",IF(AND(I8>=0.15,U8<0),"High Discount",IF(S8>H8,"Delivery Cost Exceeded Order Value","Low Order Value / Thin Margin"))))) -> Order Returned
A9: ORD10013 | B9: 46035.729 | C9: Yash Reddy | D9: Hyderabad | E9: Website | F9: Fashion | G9: 2 | H9: 510.45 | I9: 0.1 | J9: 29 | K9: =IF(N9="Cancelled",0,IF(N9="Returned",J9,H9*(1-I9)+J9)) -> 488.405 | L9: Credit/Debit Card | M9: Harpreet Singh | N9: Delivered | O9: 26 | P9: 5 | Q9: =TEXT(tblOrders[[#This Row],[Order Date]],"mmm-yyyy") -> Jan-2026 | R9: =IF(N9="Cancelled",0,H9*INDEX(Assumptions!$C$7:$C$12,MATCH(F9,Assumptions!$B$7:$B$12,0))) -> 280.7475 | S9: =IF(N9="Cancelled",Assumptions!$C$19,IF(N9="Returned",Assumptions!$C$17+O9*Assumptions!$C$18+Assumptions!$C$20,Assumptions!$C$17+O9*Assumptions!$C$18)) -> 32.8 | T9: =R9+S9 -> 313.5475 | U9: =K9-T9 -> 174.8575 | V9: =IF(U9>0,U9,0) -> 174.8575 | W9: =IF(U9>0,U9/H9,0) -> 0.34255559 | X9: =IF(U9<0,-U9,0) -> 0 | Y9: =IF(U9<0,-U9/H9,0) -> 0 | Z9: =IF(U9>=0,"Profitable",IF(N9="Cancelled","Order Cancelled",IF(N9="Returned","Order Returned",IF(AND(I9>=0.15,U9<0),"High Discount",IF(S9>H9,"Delivery Cost Exceeded Order Value","Low Order Value / Thin Margin"))))) -> Profitable
A10: ORD10084 | B10: 46036.424 | C10: Aryan Joshi | D10: Pune | E10: Mobile App | F10: Food & Beverage | G10: 1 | H10: 317.68 | I10: 0.15 | J10: 59 | K10: =IF(N10="Cancelled",0,IF(N10="Returned",J10,H10*(1-I10)+J10)) -> 329.028 | L10: Net Banking | M10: Gaurav Nanda | N10: Delivered | O10: 71 | P10: 4 | Q10: =TEXT(tblOrders[[#This Row],[Order Date]],"mmm-yyyy") -> Jan-2026 | R10: =IF(N10="Cancelled",0,H10*INDEX(Assumptions!$C$7:$C$12,MATCH(F10,Assumptions!$B$7:$B$12,0))) -> 142.956 | S10: =IF(N10="Cancelled",Assumptions!$C$19,IF(N10="Returned",Assumptions!$C$17+O10*Assumptions!$C$18+Assumptions!$C$20,Assumptions!$C$17+O10*Assumptions!$C$18)) -> 46.3 | T10: =R10+S10 -> 189.256 | U10: =K10-T10 -> 139.772 | V10: =IF(U10>0,U10,0) -> 139.772 | W10: =IF(U10>0,U10/H10,0) -> 0.43997734 | X10: =IF(U10<0,-U10,0) -> 0 | Y10: =IF(U10<0,-U10/H10,0) -> 0 | Z10: =IF(U10>=0,"Profitable",IF(N10="Cancelled","Order Cancelled",IF(N10="Returned","Order Returned",IF(AND(I10>=0.15,U10<0),"High Discount",IF(S10>H10,"Delivery Cost Exceeded Order Value","Low Order Value / Thin Margin"))))) -> Profitable
A11: ORD10153 | B11: 46041.494 | C11: Simran Reddy | D11: Kolkata | E11: Website | F11: Food & Beverage | G11: 5 | H11: 273.61 | I11: 0 | J11: 49 | K11: =IF(N11="Cancelled",0,IF(N11="Returned",J11,H11*(1-I11)+J11)) -> 49 | L11: Cash on Delivery | M11: Gaurav Nanda | N11: Returned | O11: 19 | P11: 1 | Q11: =TEXT(tblOrders[[#This Row],[Order Date]],"mmm-yyyy") -> Jan-2026 | R11: =IF(N11="Cancelled",0,H11*INDEX(Assumptions!$C$7:$C$12,MATCH(F11,Assumptions!$B$7:$B$12,0))) -> 123.1245 | S11: =IF(N11="Cancelled",Assumptions!$C$19,IF(N11="Returned",Assumptions!$C$17+O11*Assumptions!$C$18+Assumptions!$C$20,Assumptions!$C$17+O11*Assumptions!$C$18)) -> 50.7 | T11: =R11+S11 -> 173.8245 | U11: =K11-T11 -> -124.8245 | V11: =IF(U11>0,U11,0) -> 0 | W11: =IF(U11>0,U11/H11,0) -> 0 | X11: =IF(U11<0,-U11,0) -> 124.8245 | Y11: =IF(U11<0,-U11/H11,0) -> 0.45621322 | Z11: =IF(U11>=0,"Profitable",IF(N11="Cancelled","Order Cancelled",IF(N11="Returned","Order Returned",IF(AND(I11>=0.15,U11<0),"High Discount",IF(S11>H11,"Delivery Cost Exceeded Order Value","Low Order Value / Thin Margin"))))) -> Order Returned
A12: ORD10008 | B12: 46041.819 | C12: Rohan Agarwal | D12: Kolkata | E12: Mobile App | F12: Grocery | G12: 1 | H12: 1052.62 | I12: 0 | J12: 0 | K12: =IF(N12="Cancelled",0,IF(N12="Returned",J12,H12*(1-I12)+J12)) -> 1052.62 | L12: Credit/Debit Card | M12: Sunil Barik | N12: Delivered | O12: 80 | P12: 3 | Q12: =TEXT(tblOrders[[#This Row],[Order Date]],"mmm-yyyy") -> Jan-2026 | R12: =IF(N12="Cancelled",0,H12*INDEX(Assumptions!$C$7:$C$12,MATCH(F12,Assumptions!$B$7:$B$12,0))) -> 821.0436 | S12: =IF(N12="Cancelled",Assumptions!$C$19,IF(N12="Returned",Assumptions!$C$17+O12*Assumptions!$C$18+Assumptions!$C$20,Assumptions!$C$17+O12*Assumptions!$C$18)) -> 49 | T12: =R12+S12 -> 870.0436 | U12: =K12-T12 -> 182.5764 | V12: =IF(U12>0,U12,0) -> 182.5764 | W12: =IF(U12>0,U12/H12,0) -> 0.17344949 | X12: =IF(U12<0,-U12,0) -> 0 | Y12: =IF(U12<0,-U12/H12,0) -> 0 | Z12: =IF(U12>=0,"Profitable",IF(N12="Cancelled","Order Cancelled",IF(N12="Returned","Order Returned",IF(AND(I12>=0.15,U12<0),"High Discount",IF(S12>H12,"Delivery Cost Exceeded Order Value","Low Order Value / Thin Margin"))))) -> Profitable
A13: ORD10192 | B13: 46042.442 | C13: Yash Patel | D13: Pune | E13: Mobile App | F13: Grocery | G13: 1 | H13: 158.47 | I13: 0 | J13: 29 | K13: =IF(N13="Cancelled",0,IF(N13="Returned",J13,H13*(1-I13)+J13)) -> 187.47 | L13: Net Banking | M13: Harpreet Singh | N13: Delivered | O13: 79 | P13: 3 | Q13: =TEXT(tblOrders[[#This Row],[Order Date]],"mmm-yyyy") -> Jan-2026 | R13: =IF(N13="Cancelled",0,H13*INDEX(Assumptions!$C$7:$C$12,MATCH(F13,Assumptions!$B$7:$B$12,0))) -> 123.6066 | S13: =IF(N13="Cancelled",Assumptions!$C$19,IF(N13="Returned",Assumptions!$C$17+O13*Assumptions!$C$18+Assumptions!$C$20,Assumptions!$C$17+O13*Assumptions!$C$18)) -> 48.7 | T13: =R13+S13 -> 172.3066 | U13: =K13-T13 -> 15.1634 | V13: =IF(U13>0,U13,0) -> 15.1634 | W13: =IF(U13>0,U13/H13,0) -> 0.09568625 | X13: =IF(U13<0,-U13,0) -> 0 | Y13: =IF(U13<0,-U13/H13,0) -> 0 | Z13: =IF(U13>=0,"Profitable",IF(N13="Cancelled","Order Cancelled",IF(N13="Returned","Order Returned",IF(AND(I13>=0.15,U13<0),"High Discount",IF(S13>H13,"Delivery Cost Exceeded Order Value","Low Order Value / Thin Margin"))))) -> Profitable
A14: ORD10208 | B14: 46042.733 | C14: Arjun Iyer | D14: Pune | E14: Mobile App | F14: Grocery | G14: 2 | H14: 398.61 | I14: 0 | J14: 49 | K14: =IF(N14="Cancelled",0,IF(N14="Returned",J14,H14*(1-I14)+J14)) -> 447.61 | L14: Net Banking | M14: Omkar Naik | N14: Delivered | O14: 59 | P14: 4 | Q14: =TEXT(tblOrders[[#This Row],[Order Date]],"mmm-yyyy") -> Jan-2026 | R14: =IF(N14="Cancelled",0,H14*INDEX(Assumptions!$C$7:$C$12,MATCH(F14,Assumptions!$B$7:$B$12,0))) -> 310.9158 | S14: =IF(N14="Cancelled",Assumptions!$C$19,IF(N14="Returned",Assumptions!$C$17+O14*Assumptions!$C$18+Assumptions!$C$20,Assumptions!$C$17+O14*Assumptions!$C$18)) -> 42.7 | T14: =R14+S14 -> 353.6158 | U14: =K14-T14 -> 93.9942 | V14: =IF(U14>0,U14,0) -> 93.9942 | W14: =IF(U14>0,U14/H14,0) -> 0.23580492 | X14: =IF(U14<0,-U14,0) -> 0 | Y14: =IF(U14<0,-U14/H14,0) -> 0 | Z14: =IF(U14>=0,"Profitable",IF(N14="Cancelled","Order Cancelled",IF(N14="Returned","Order Returned",IF(AND(I14>=0.15,U14<0),"High Discount",IF(S14>H14,"Delivery Cost Exceeded Order Value","Low Order Value / Thin Margin"))))) -> Profitable
A15: ORD10143 | B15: 46042.942 | C15: Tanya Das | D15: Kolkata | E15: Website | F15: Grocery | G15: 5 | H15: 362.26 | I15: 0.1 | J15: 39 | K15: =IF(N15="Cancelled",0,IF(N15="Returned",J15,H15*(1-I15)+J15)) -> 365.034 | L15: Credit/Debit Card | M15: Bikash Mallick | N15: Delivered | O15: 84 | P15: 4 | Q15: =TEXT(tblOrders[[#This Row],[Order Date]],"mmm-yyyy") -> Jan-2026 | R15: =IF(N15="Cancelled",0,H15*INDEX(Assumptions!$C$7:$C$12,MATCH(F15,Assumptions!$B$7:$B$12,0))) -> 282.5628 | S15: =IF(N15="Cancelled",Assumptions!$C$19,IF(N15="Returned",Assumptions!$C$17+O15*Assumptions!$C$18+Assumptions!$C$20,Assumptions!$C$17+O15*Assumptions!$C$18)) -> 50.2 | T15: =R15+S15 -> 332.7628 | U15: =K15-T15 -> 32.2712 | V15: =IF(U15>0,U15,0) -> 32.2712 | W15: =IF(U15>0,U15/H15,0) -> 0.089082979 | X15: =IF(U15<0,-U15,0) -> 0 | Y15: =IF(U15<0,-U15/H15,0) -> 0 | Z15: =IF(U15>=0,"Profitable",IF(N15="Cancelled","Order Cancelled",IF(N15="Returned","Order Returned",IF(AND(I15>=0.15,U15<0),"High Discount",IF(S15>H15,"Delivery Cost Exceeded Order Value","Low Order Value / Thin Margin"))))) -> Profitable
A16: ORD10019 | B16: 46042.947 | C16: Ishaan Bose | D16: Hyderabad | E16: Mobile App | F16: Home & Living | G16: 3 | H16: 3578.56 | I16: 0 | J16: 0 | K16: =IF(N16="Cancelled",0,IF(N16="Returned",J16,H16*(1-I16)+J16)) -> 3578.56 | L16: Net Banking | M16: Ramesh Yadav | N16: Delivered | O16: 57 | P16: 4 | Q16: =TEXT(tblOrders[[#This Row],[Order Date]],"mmm-yyyy") -> Jan-2026 | R16: =IF(N16="Cancelled",0,H16*INDEX(Assumptions!$C$7:$C$12,MATCH(F16,Assumptions!$B$7:$B$12,0))) -> 2326.064 | S16: =IF(N16="Cancelled",Assumptions!$C$19,IF(N16="Returned",Assumptions!$C$17+O16*Assumptions!$C$18+Assumptions!$C$20,Assumptions!$C$17+O16*Assumptions!$C$18)) -> 42.1 | T16: =R16+S16 -> 2368.164 | U16: =K16-T16 -> 1210.396 | V16: =IF(U16>0,U16,0) -> 1210.396 | W16: =IF(U16>0,U16/H16,0) -> 0.33823549 | X16: =IF(U16<0,-U16,0) -> 0 | Y16: =IF(U16<0,-U16/H16,0) -> 0 | Z16: =IF(U16>=0,"Profitable",IF(N16="Cancelled","Order Cancelled",IF(N16="Returned","Order Returned",IF(AND(I16>=0.15,U16<0),"High Discount",IF(S16>H16,"Delivery Cost Exceeded Order Value","Low Order Value / Thin Margin"))))) -> Profitable
A17: ORD10077 | B17: 46043.568 | C17: Sahil Ghosh | D17: Mumbai | E17: Mobile App | F17: Grocery | G17: 5 | H17: 814.73 | I17: 0.1 | J17: 49 | K17: =IF(N17="Cancelled",0,IF(N17="Returned",J17,H17*(1-I17)+J17)) -> 49 | L17: Net Banking | M17: Omkar Naik | N17: Returned | O17: 85 | P17: 2 | Q17: =TEXT(tblOrders[[#This Row],[Order Date]],"mmm-yyyy") -> Jan-2026 | R17: =IF(N17="Cancelled",0,H17*INDEX(Assumptions!$C$7:$C$12,MATCH(F17,Assumptions!$B$7:$B$12,0))) -> 635.4894 | S17: =IF(N17="Cancelled",Assumptions!$C$19,IF(N17="Returned",Assumptions!$C$17+O17*Assumptions!$C$18+Assumptions!$C$20,Assumptions!$C$17+O17*Assumptions!$C$18)) -> 70.5 | T17: =R17+S17 -> 705.9894 | U17: =K17-T17 -> -656.9894 | V17: =IF(U17>0,U17,0) -> 0 | W17: =IF(U17>0,U17/H17,0) -> 0 | X17: =IF(U17<0,-U17,0) -> 656.9894 | Y17: =IF(U17<0,-U17/H17,0) -> 0.80638911 | Z17: =IF(U17>=0,"Profitable",IF(N17="Cancelled","Order Cancelled",IF(N17="Returned","Order Returned",IF(AND(I17>=0.15,U17<0),"High Discount",IF(S17>H17,"Delivery Cost Exceeded Order Value","Low Order Value / Thin Margin"))))) -> Order Returned
A18: ORD10042 | B18: 46044.49 | C18: Sneha Kapoor | D18: Hyderabad | E18: Mobile App | F18: Fashion | G18: 2 | H18: 2855.25 | I18: 0.15 | J18: 0 | K18: =IF(N18="Cancelled",0,IF(N18="Returned",J18,H18*(1-I18)+J18)) -> 2426.9625 | L18: Net Banking | M18: Jyoti Panda | N18: Delivered | O18: 20 | P18: 3 | Q18: =TEXT(tblOrders[[#This Row],[Order Date]],"mmm-yyyy") -> Jan-2026 | R18: =IF(N18="Cancelled",0,H18*INDEX(Assumptions!$C$7:$C$12,MATCH(F18,Assumptions!$B$7:$B$12,0))) -> 1570.3875 | S18: =IF(N18="Cancelled",Assumptions!$C$19,IF(N18="Returned",Assumptions!$C$17+O18*Assumptions!$C$18+Assumptions!$C$20,Assumptions!$C$17+O18*Assumptions!$C$18)) -> 31 | T18: =R18+S18 -> 1601.3875 | U18: =K18-T18 -> 825.575 | V18: =IF(U18>0,U18,0) -> 825.575 | W18: =IF(U18>0,U18/H18,0) -> 0.28914281 | X18: =IF(U18<0,-U18,0) -> 0 | Y18: =IF(U18<0,-U18/H18,0) -> 0 | Z18: =IF(U18>=0,"Profitable",IF(N18="Cancelled","Order Cancelled",IF(N18="Returned","Order Returned",IF(AND(I18>=0.15,U18<0),"High Discount",IF(S18>H18,"Delivery Cost Exceeded Order Value","Low Order Value / Thin Margin"))))) -> Profitable
... A29: ORD10062 | B29: 46048.861 | C29: Divya Nair | D29: Hyderabad | E29: Mobile App | F29: Food & Beverage | G29: 2 | H29: 655.2 | I29: 0 | J29: 29 | K29: =IF(N29="Cancelled",0,IF(N29="Returned",J29,H29*(1-I29)+J29)) -> 684.2 | L29: Cash on Delivery | M29: Lalita Rout | N29: Delivered | O29: 55 | P29: 4 | Q29: =TEXT(tblOrders[[#This Row],[Order Date]],"mmm-yyyy") -> Jan-2026 | R29: =IF(N29="Cancelled",0,H29*INDEX(Assumptions!$C$7:$C$12,MATCH(F29,Assumptions!$B$7:$B$12,0))) -> 294.84 | S29: =IF(N29="Cancelled",Assumptions!$C$19,IF(N29="Returned",Assumptions!$C$17+O29*Assumptions!$C$18+Assumptions!$C$20,Assumptions!$C$17+O29*Assumptions!$C$18)) -> 41.5 | T29: =R29+S29 -> 336.34 | U29: =K29-T29 -> 347.86 | V29: =IF(U29>0,U29,0) -> 347.86 | W29: =IF(U29>0,U29/H29,0) -> 0.53092186 | X29: =IF(U29<0,-U29,0) -> 0 | Y29: =IF(U29<0,-U29/H29,0) -> 0 | Z29: =IF(U29>=0,"Profitable",IF(N29="Cancelled","Order Cancelled",IF(N29="Returned","Order Returned",IF(AND(I29>=0.15,U29<0),"High Discount",IF(S29>H29,"Delivery Cost Exceeded Order Value","Low Order Value / Thin Margin"))))) -> Profitable
A30: ORD10078 | B30: 46048.864 | C30: Karan Malhotra | D30: Mumbai | E30: Mobile App | F30: Grocery | G30: 5 | H30: 906.88 | I30: 0 | J30: 59 | K30: =IF(N30="Cancelled",0,IF(N30="Returned",J30,H30*(1-I30)+J30)) -> 0 | L30: Net Banking | M30: Nisha Pradhan | N30: Cancelled | Q30: =TEXT(tblOrders[[#This Row],[Order Date]],"mmm-yyyy") -> Jan-2026 | R30: =IF(N30="Cancelled",0,H30*INDEX(Assumptions!$C$7:$C$12,MATCH(F30,Assumptions!$B$7:$B$12,0))) -> 0 | S30: =IF(N30="Cancelled",Assumptions!$C$19,IF(N30="Returned",Assumptions!$C$17+O30*Assumptions!$C$18+Assumptions!$C$20,Assumptions!$C$17+O30*Assumptions!$C$18)) -> 15 | T30: =R30+S30 -> 15 | U30: =K30-T30 -> -15 | V30: =IF(U30>0,U30,0) -> 0 | W30: =IF(U30>0,U30/H30,0) -> 0 | X30: =IF(U30<0,-U30,0) -> 15 | Y30: =IF(U30<0,-U30/H30,0) -> 0.016540226 | Z30: =IF(U30>=0,"Profitable",IF(N30="Cancelled","Order Cancelled",IF(N30="Returned","Order Returned",IF(AND(I30>=0.15,U30<0),"High Discount",IF(S30>H30,"Delivery Cost Exceeded Order Value","Low Order Value / Thin Margin"))))) -> Order Cancelled
A31: ORD10193 | B31: 46049.558 | C31: Rahul Bose | D31: Hyderabad | E31: Mobile App | F31: Pharmacy | G31: 2 | H31: 991.04 | I31: 0.15 | J31: 39 | K31: =IF(N31="Cancelled",0,IF(N31="Returned",J31,H31*(1-I31)+J31)) -> 881.384 | L31: UPI/Wallet | M31: Farhan Ali | N31: Delivered | O31: 19 | P31: 5 | Q31: =TEXT(tblOrders[[#This Row],[Order Date]],"mmm-yyyy") -> Jan-2026 | R31: =IF(N31="Cancelled",0,H31*INDEX(Assumptions!$C$7:$C$12,MATCH(F31,Assumptions!$B$7:$B$12,0))) -> 693.728 | S31: =IF(N31="Cancelled",Assumptions!$C$19,IF(N31="Returned",Assumptions!$C$17+O31*Assumptions!$C$18+Assumptions!$C$20,Assumptions!$C$17+O31*Assumptions!$C$18)) -> 30.7 | T31: =R31+S31 -> 724.428 | U31: =K31-T31 -> 156.956 | V31: =IF(U31>0,U31,0) -> 156.956 | W31: =IF(U31>0,U31/H31,0) -> 0.15837504 | X31: =IF(U31<0,-U31,0) -> 0 | Y31: =IF(U31<0,-U31/H31,0) -> 0 | Z31: =IF(U31>=0,"Profitable",IF(N31="Cancelled","Order Cancelled",IF(N31="Returned","Order Returned",IF(AND(I31>=0.15,U31<0),"High Discount",IF(S31>H31,"Delivery Cost Exceeded Order Value","Low Order Value / Thin Margin"))))) -> Profitable
A32: ORD10010 | B32: 46050.467 | C32: Dev Pillai | D32: Bhubaneswar | E32: Mobile App | F32: Grocery | G32: 4 | H32: 342.66 | I32: 0.05 | J32: 39 | K32: =IF(N32="Cancelled",0,IF(N32="Returned",J32,H32*(1-I32)+J32)) -> 364.527 | L32: UPI/Wallet | M32: Ramesh Yadav | N32: Delivered | O32: 88 | P32: 3 | Q32: =TEXT(tblOrders[[#This Row],[Order Date]],"mmm-yyyy") -> Jan-2026 | R32: =IF(N32="Cancelled",0,H32*INDEX(Assumptions!$C$7:$C$12,MATCH(F32,Assumptions!$B$7:$B$12,0))) -> 267.2748 | S32: =IF(N32="Cancelled",Assumptions!$C$19,IF(N32="Returned",Assumptions!$C$17+O32*Assumptions!$C$18+Assumptions!$C$20,Assumptions!$C$17+O32*Assumptions!$C$18)) -> 51.4 | T32: =R32+S32 -> 318.6748 | U32: =K32-T32 -> 45.8522 | V32: =IF(U32>0,U32,0) -> 45.8522 | W32: =IF(U32>0,U32/H32,0) -> 0.13381253 | X32: =IF(U32<0,-U32,0) -> 0 | Y32: =IF(U32<0,-U32/H32,0) -> 0 | Z32: =IF(U32>=0,"Profitable",IF(N32="Cancelled","Order Cancelled",IF(N32="Returned","Order Returned",IF(AND(I32>=0.15,U32<0),"High Discount",IF(S32>H32,"Delivery Cost Exceeded Order Value","Low Order Value / Thin Margin"))))) -> Profitable
A33: ORD10148 | B33: 46051.369 | C33: Yash Malhotra | D33: Hyderabad | E33: Mobile App | F33: Food & Beverage | G33: 1 | H33: 292.53 | I33: 0 | J33: 29 | K33: =IF(N33="Cancelled",0,IF(N33="Returned",J33,H33*(1-I33)+J33)) -> 321.53 | L33: UPI/Wallet | M33: Ramesh Yadav | N33: Delivered | O33: 24 | P33: 3 | Q33: =TEXT(tblOrders[[#This Row],[Order Date]],"mmm-yyyy") -> Jan-2026 | R33: =IF(N33="Cancelled",0,H33*INDEX(Assumptions!$C$7:$C$12,MATCH(F33,Assumptions!$B$7:$B$12,0))) -> 131.6385 | S33: =IF(N33="Cancelled",Assumptions!$C$19,IF(N33="Returned",Assumptions!$C$17+O33*Assumptions!$C$18+Assumptions!$C$20,Assumptions!$C$17+O33*Assumptions!$C$18)) -> 32.2 | T33: =R33+S33 -> 163.8385 | U33: =K33-T33 -> 157.6915 | V33: =IF(U33>0,U33,0) -> 157.6915 | W33: =IF(U33>0,U33/H33,0) -> 0.53906095 | X33: =IF(U33<0,-U33,0) -> 0 | Y33: =IF(U33<0,-U33/H33,0) -> 0 | Z33: =IF(U33>=0,"Profitable",IF(N33="Cancelled","Order Cancelled",IF(N33="Returned","Order Returned",IF(AND(I33>=0.15,U33<0),"High Discount",IF(S33>H33,"Delivery Cost Exceeded Order Value","Low Order Value / Thin Margin"))))) -> Profitable
A34: ORD10220 | B34: 46051.898 | C34: Rohan Gupta | D34: Mumbai | E34: Website | F34: Pharmacy | G34: 3 | H34: 1080.44 | I34: 0.15 | J34: 0 | K34: =IF(N34="Cancelled",0,IF(N34="Returned",J34,H34*(1-I34)+J34)) -> 918.374 | L34: Net Banking | M34: Kunal Mehta | N34: Delivered | O34: 61 | P34: 4 | Q34: =TEXT(tblOrders[[#This Row],[Order Date]],"mmm-yyyy") -> Jan-2026 | R34: =IF(N34="Cancelled",0,H34*INDEX(Assumptions!$C$7:$C$12,MATCH(F34,Assumptions!$B$7:$B$12,0))) -> 756.308 | S34: =IF(N34="Cancelled",Assumptions!$C$19,IF(N34="Returned",Assumptions!$C$17+O34*Assumptions!$C$18+Assumptions!$C$20,Assumptions!$C$17+O34*Assumptions!$C$18)) -> 43.3 | T34: =R34+S34 -> 799.608 | U34: =K34-T34 -> 118.766 | V34: =IF(U34>0,U34,0) -> 118.766 | W34: =IF(U34>0,U34/H34,0) -> 0.10992373 | X34: =IF(U34<0,-U34,0) -> 0 | Y34: =IF(U34<0,-U34/H34,0) -> 0 | Z34: =IF(U34>=0,"Profitable",IF(N34="Cancelled","Order Cancelled",IF(N34="Returned","Order Returned",IF(AND(I34>=0.15,U34<0),"High Discount",IF(S34>H34,"Delivery Cost Exceeded Order Value","Low Order Value / Thin Margin"))))) -> Profitable
A35: ORD10179 | B35: 46052.529 | C35: Varun Singh | D35: Pune | E35: Mobile App | F35: Pharmacy | G35: 6 | H35: 525.03 | I35: 0.05 | J35: 59 | K35: =IF(N35="Cancelled",0,IF(N35="Returned",J35,H35*(1-I35)+J35)) -> 557.7785 | L35: UPI/Wallet | M35: Farhan Ali | N35: Delivered | O35: 76 | P35: 5 | Q35: =TEXT(tblOrders[[#This Row],[Order Date]],"mmm-yyyy") -> Jan-2026 | R35: =IF(N35="Cancelled",0,H35*INDEX(Assumptions!$C$7:$C$12,MATCH(F35,Assumptions!$B$7:$B$12,0))) -> 367.521 | S35: =IF(N35="Cancelled",Assumptions!$C$19,IF(N35="Returned",Assumptions!$C$17+O35*Assumptions!$C$18+Assumptions!$C$20,Assumptions!$C$17+O35*Assumptions!$C$18)) -> 47.8 | T35: =R35+S35 -> 415.321 | U35: =K35-T35 -> 142.4575 | V35: =IF(U35>0,U35,0) -> 142.4575 | W35: =IF(U35>0,U35/H35,0) -> 0.27133211 | X35: =IF(U35<0,-U35,0) -> 0 | Y35: =IF(U35<0,-U35/H35,0) -> 0 | Z35: =IF(U35>=0,"Profitable",IF(N35="Cancelled","Order Cancelled",IF(N35="Returned","Order Returned",IF(AND(I35>=0.15,U35<0),"High Discount",IF(S35>H35,"Delivery Cost Exceeded Order Value","Low Order Value / Thin Margin"))))) -> Profitable
A36: ORD10050 | B36: 46052.676 | C36: Nikhil Kapoor | D36: Chennai | E36: Website | F36: Food & Beverage | G36: 2 | H36: 157.13 | I36: 0 | J36: 49 | K36: =IF(N36="Cancelled",0,IF(N36="Returned",J36,H36*(1-I36)+J36)) -> 206.13 | L36: Cash on Delivery | M36: Jyoti Panda | N36: Delivered | O36: 77 | P36: 5 | Q36: =TEXT(tblOrders[[#This Row],[Order Date]],"mmm-yyyy") -> Jan-2026 | R36: =IF(N36="Cancelled",0,H36*INDEX(Assumptions!$C$7:$C$12,MATCH(F36,Assumptions!$B$7:$B$12,0))) -> 70.7085 | S36: =IF(N36="Cancelled",Assumptions!$C$19,IF(N36="Returned",Assumptions!$C$17+O36*Assumptions!$C$18+Assumptions!$C$20,Assumptions!$C$17+O36*Assumptions!$C$18)) -> 48.1 | T36: =R36+S36 -> 118.8085 | U36: =K36-T36 -> 87.3215 | V36: =IF(U36>0,U36,0) -> 87.3215 | W36: =IF(U36>0,U36/H36,0) -> 0.55572774 | X36: =IF(U36<0,-U36,0) -> 0 | Y36: =IF(U36<0,-U36/H36,0) -> 0 | Z36: =IF(U36>=0,"Profitable",IF(N36="Cancelled","Order Cancelled",IF(N36="Returned","Order Returned",IF(AND(I36>=0.15,U36<0),"High Discount",IF(S36>H36,"Delivery Cost Exceeded Order Value","Low Order Value / Thin Margin"))))) -> Profitable
A37: ORD10017 | B37: 46052.921 | C37: Arjun Verma | D37: Pune | E37: Mobile App | F37: Food & Beverage | G37: 3 | H37: 583.86 | I37: 0.15 | J37: 49 | K37: =IF(N37="Cancelled",0,IF(N37="Returned",J37,H37*(1-I37)+J37)) -> 545.281 | L37: Credit/Debit Card | M37: Pankaj Dey | N37: Delivered | O37: 51 | P37: 5 | Q37: =TEXT(tblOrders[[#This Row],[Order Date]],"mmm-yyyy") -> Jan-2026 | R37: =IF(N37="Cancelled",0,H37*INDEX(Assumptions!$C$7:$C$12,MATCH(F37,Assumptions!$B$7:$B$12,0))) -> 262.737 | S37: =IF(N37="Cancelled",Assumptions!$C$19,IF(N37="Returned",Assumptions!$C$17+O37*Assumptions!$C$18+Assumptions!$C$20,Assumptions!$C$17+O37*Assumptions!$C$18)) -> 40.3 | T37: =R37+S37 -> 303.037 | U37: =K37-T37 -> 242.244 | V37: =IF(U37>0,U37,0) -> 242.244 | W37: =IF(U37>0,U37/H37,0) -> 0.41490083 | X37: =IF(U37<0,-U37,0) -> 0 | Y37: =IF(U37<0,-U37/H37,0) -> 0 | Z37: =IF(U37>=0,"Profitable",IF(N37="Cancelled","Order Cancelled",IF(N37="Returned","Order Returned",IF(AND(I37>=0.15,U37<0),"High Discount",IF(S37>H37,"Delivery Cost Exceeded Order Value","Low Order Value / Thin Margin"))))) -> Profitable
A38: ORD10210 | B38: 46053.382 | C38: Nikhil Iyer | D38: Delhi | E38: Mobile App | F38: Pharmacy | G38: 6 | H38: 1069.57 | I38: 0 | J38: 0 | K38: =IF(N38="Cancelled",0,IF(N38="Returned",J38,H38*(1-I38)+J38)) -> 1069.57 | L38: Credit/Debit Card | M38: Anita Behera | N38: Delivered | O38: 59 | P38: 3 | Q38: =TEXT(tblOrders[[#This Row],[Order Date]],"mmm-yyyy") -> Jan-2026 | R38: =IF(N38="Cancelled",0,H38*INDEX(Assumptions!$C$7:$C$12,MATCH(F38,Assumptions!$B$7:$B$12,0))) -> 748.699 | S38: =IF(N38="Cancelled",Assumptions!$C$19,IF(N38="Returned",Assumptions!$C$17+O38*Assumptions!$C$18+Assumptions!$C$20,Assumptions!$C$17+O38*Assumptions!$C$18)) -> 42.7 | T38: =R38+S38 -> 791.399 | U38: =K38-T38 -> 278.171 | V38: =IF(U38>0,U38,0) -> 278.171 | W38: =IF(U38>0,U38/H38,0) -> 0.26007741 | X38: =IF(U38<0,-U38,0) -> 0 | Y38: =IF(U38<0,-U38/H38,0) -> 0 | Z38: =IF(U38>=0,"Profitable",IF(N38="Cancelled","Order Cancelled",IF(N38="Returned","Order Returned",IF(AND(I38>=0.15,U38<0),"High Discount",IF(S38>H38,"Delivery Cost Exceeded Order Value","Low Order Value / Thin Margin"))))) -> Profitable
A39: ORD10204 | B39: 46053.697 | C39: Aryan Singh | D39: Delhi | E39: Mobile App | F39: Home & Living | G39: 5 | H39: 5892.2 | I39: 0.05 | J39: 0 | K39: =IF(N39="Cancelled",0,IF(N39="Returned",J39,H39*(1-I39)+J39)) -> 0 | L39: UPI/Wallet | M39: Jyoti Panda | N39: Cancelled | Q39: =TEXT(tblOrders[[#This Row],[Order Date]],"mmm-yyyy") -> Jan-2026 | R39: =IF(N39="Cancelled",0,H39*INDEX(Assumptions!$C$7:$C$12,MATCH(F39,Assumptions!$B$7:$B$12,0))) -> 0 | S39: =IF(N39="Cancelled",Assumptions!$C$19,IF(N39="Returned",Assumptions!$C$17+O39*Assumptions!$C$18+Assumptions!$C$20,Assumptions!$C$17+O39*Assumptions!$C$18)) -> 15 | T39: =R39+S39 -> 15 | U39: =K39-T39 -> -15 | V39: =IF(U39>0,U39,0) -> 0 | W39: =IF(U39>0,U39/H39,0) -> 0 | X39: =IF(U39<0,-U39,0) -> 15 | Y39: =IF(U39<0,-U39/H39,0) -> 0.0025457384 | Z39: =IF(U39>=0,"Profitable",IF(N39="Cancelled","Order Cancelled",IF(N39="Returned","Order Returned",IF(AND(I39>=0.15,U39<0),"High Discount",IF(S39>H39,"Delivery Cost Exceeded Order Value","Low Order Value / Thin Margin"))))) -> Order Cancelled
A40: ORD10126 | B40: 46055.392 | C40: Vivaan Verma | D40: Bhubaneswar | E40: Website | F40: Electronics | G40: 5 | H40: 14133.07 | I40: 0.2 | J40: 0 | K40: =IF(N40="Cancelled",0,IF(N40="Returned",J40,H40*(1-I40)+J40)) -> 11306.456 | L40: Credit/Debit Card | M40: Rekha Sethi | N40: Delivered | O40: 83 | P40: 4 | Q40: =TEXT(tblOrders[[#This Row],[Order Date]],"mmm-yyyy") -> Feb-2026 | R40: =IF(N40="Cancelled",0,H40*INDEX(Assumptions!$C$7:$C$12,MATCH(F40,Assumptions!$B$7:$B$12,0))) -> 12437.102 | S40: =IF(N40="Cancelled",Assumptions!$C$19,IF(N40="Returned",Assumptions!$C$17+O40*Assumptions!$C$18+Assumptions!$C$20,Assumptions!$C$17+O40*Assumptions!$C$18)) -> 49.9 | T40: =R40+S40 -> 12487.002 | U40: =K40-T40 -> -1180.5456 | V40: =IF(U40>0,U40,0) -> 0 | W40: =IF(U40>0,U40/H40,0) -> 0 | X40: =IF(U40<0,-U40,0) -> 1180.5456 | Y40: =IF(U40<0,-U40/H40,0) -> 0.083530726 | Z40: =IF(U40>=0,"Profitable",IF(N40="Cancelled","Order Cancelled",IF(N40="Returned","Order Returned",IF(AND(I40>=0.15,U40<0),"High Discount",IF(S40>H40,"Delivery Cost Exceeded Order Value","Low Order Value / Thin Margin"))))) -> High Discount
A41: ORD10212 | B41: 46056.494 | C41: Kritika Nair | D41: Pune | E41: Website | F41: Fashion | G41: 6 | H41: 610.95 | I41: 0.1 | J41: 49 | K41: =IF(N41="Cancelled",0,IF(N41="Returned",J41,H41*(1-I41)+J41)) -> 598.855 | L41: UPI/Wallet | M41: Omkar Naik | N41: Delivered | O41: 26 | P41: 3 | Q41: =TEXT(tblOrders[[#This Row],[Order Date]],"mmm-yyyy") -> Feb-2026 | R41: =IF(N41="Cancelled",0,H41*INDEX(Assumptions!$C$7:$C$12,MATCH(F41,Assumptions!$B$7:$B$12,0))) -> 336.0225 | S41: =IF(N41="Cancelled",Assumptions!$C$19,IF(N41="Returned",Assumptions!$C$17+O41*Assumptions!$C$18+Assumptions!$C$20,Assumptions!$C$17+O41*Assumptions!$C$18)) -> 32.8 | T41: =R41+S41 -> 368.8225 | U41: =K41-T41 -> 230.0325 | V41: =IF(U41>0,U41,0) -> 230.0325 | W41: =IF(U41>0,U41/H41,0) -> 0.37651608 | X41: =IF(U41<0,-U41,0) -> 0 | Y41: =IF(U41<0,-U41/H41,0) -> 0 | Z41: =IF(U41>=0,"Profitable",IF(N41="Cancelled","Order Cancelled",IF(N41="Returned","Order Returned",IF(AND(I41>=0.15,U41<0),"High Discount",IF(S41>H41,"Delivery Cost Exceeded Order Value","Low Order Value / Thin Margin"))))) -> Profitable
A42: ORD10122 | B42: 46056.849 | C42: Yash Ghosh | D42: Mumbai | E42: Mobile App | F42: Fashion | G42: 2 | H42: 2025.95 | I42: 0 | J42: 0 | K42: =IF(N42="Cancelled",0,IF(N42="Returned",J42,H42*(1-I42)+J42)) -> 2025.95 | L42: Net Banking | M42: Jyoti Panda | N42: Delivered | O42: 30 | P42: 3 | Q42: =TEXT(tblOrders[[#This Row],[Order Date]],"mmm-yyyy") -> Feb-2026 | R42: =IF(N42="Cancelled",0,H42*INDEX(Assumptions!$C$7:$C$12,MATCH(F42,Assumptions!$B$7:$B$12,0))) -> 1114.2725 | S42: =IF(N42="Cancelled",Assumptions!$C$19,IF(N42="Returned",Assumptions!$C$17+O42*Assumptions!$C$18+Assumptions!$C$20,Assumptions!$C$17+O42*Assumptions!$C$18)) -> 34 | T42: =R42+S42 -> 1148.2725 | U42: =K42-T42 -> 877.6775 | V42: =IF(U42>0,U42,0) -> 877.6775 | W42: =IF(U42>0,U42/H42,0) -> 0.43321775 | X42: =IF(U42<0,-U42,0) -> 0 | Y42: =IF(U42<0,-U42/H42,0) -> 0 | Z42: =IF(U42>=0,"Profitable",IF(N42="Cancelled","Order Cancelled",IF(N42="Returned","Order Returned",IF(AND(I42>=0.15,U42<0),"High Discount",IF(S42>H42,"Delivery Cost Exceeded Order Value","Low Order Value / Thin Margin"))))) -> Profitable
A43: ORD10186 | B43: 46057.868 | C43: Ananya Nair | D43: Chennai | E43: Mobile App | F43: Fashion | G43: 3 | H43: 3508.08 | I43: 0 | J43: 0 | K43: =IF(N43="Cancelled",0,IF(N43="Returned",J43,H43*(1-I43)+J43)) -> 3508.08 | L43: Credit/Debit Card | M43: Manoj Tiwari | N43: Delivered | O43: 59 | P43: 3 | Q43: =TEXT(tblOrders[[#This Row],[Order Date]],"mmm-yyyy") -> Feb-2026 | R43: =IF(N43="Cancelled",0,H43*INDEX(Assumptions!$C$7:$C$12,MATCH(F43,Assumptions!$B$7:$B$12,0))) -> 1929.444 | S43: =IF(N43="Cancelled",Assumptions!$C$19,IF(N43="Returned",Assumptions!$C$17+O43*Assumptions!$C$18+Assumptions!$C$20,Assumptions!$C$17+O43*Assumptions!$C$18)) -> 42.7 | T43: =R43+S43 -> 1972.144 | U43: =K43-T43 -> 1535.936 | V43: =IF(U43>0,U43,0) -> 1535.936 | W43: =IF(U43>0,U43/H43,0) -> 0.4378281 | X43: =IF(U43<0,-U43,0) -> 0 | Y43: =IF(U43<0,-U43/H43,0) -> 0 | Z43: =IF(U43>=0,"Profitable",IF(N43="Cancelled","Order Cancelled",IF(N43="Returned","Order Returned",IF(AND(I43>=0.15,U43<0),"High Discount",IF(S43>H43,"Delivery Cost Exceeded Order Value","Low Order Value / Thin Margin"))))) -> Profitable
A44: ORD10138 | B44: 46057.897 | C44: Kritika Singh | D44: Hyderabad | E44: Mobile App | F44: Fashion | G44: 1 | H44: 1523.53 | I44: 0.15 | J44: 0 | K44: =IF(N44="Cancelled",0,IF(N44="Returned",J44,H44*(1-I44)+J44)) -> 1295.0005 | L44: Net Banking | M44: Kunal Mehta | N44: Delivered | O44: 41 | P44: 3 | Q44: =TEXT(tblOrders[[#This Row],[Order Date]],"mmm-yyyy") -> Feb-2026 | R44: =IF(N44="Cancelled",0,H44*INDEX(Assumptions!$C$7:$C$12,MATCH(F44,Assumptions!$B$7:$B$12,0))) -> 837.9415 | S44: =IF(N44="Cancelled",Assumptions!$C$19,IF(N44="Returned",Assumptions!$C$17+O44*Assumptions!$C$18+Assumptions!$C$20,Assumptions!$C$17+O44*Assumptions!$C$18)) -> 37.3 | T44: =R44+S44 -> 875.2415 | U44: =K44-T44 -> 419.759 | V44: =IF(U44>0,U44,0) -> 419.759 | W44: =IF(U44>0,U44/H44,0) -> 0.27551738 | X44: =IF(U44<0,-U44,0) -> 0 | Y44: =IF(U44<0,-U44/H44,0) -> 0 | Z44: =IF(U44>=0,"Profitable",IF(N44="Cancelled","Order Cancelled",IF(N44="Returned","Order Returned",IF(AND(I44>=0.15,U44<0),"High Discount",IF(S44>H44,"Delivery Cost Exceeded Order Value","Low Order Value / Thin Margin"))))) -> Profitable
A45: ORD10195 | B45: 46058.47 | C45: Riya Joshi | D45: Hyderabad | E45: Mobile App | F45: Food & Beverage | G45: 5 | H45: 580.01 | I45: 0.1 | J45: 49 | K45: =IF(N45="Cancelled",0,IF(N45="Returned",J45,H45*(1-I45)+J45)) -> 571.009 | L45: UPI/Wallet | M45: Rekha Sethi | N45: Delivered | O45: 56 | P45: 3 | Q45: =TEXT(tblOrders[[#This Row],[Order Date]],"mmm-yyyy") -> Feb-2026 | R45: =IF(N45="Cancelled",0,H45*INDEX(Assumptions!$C$7:$C$12,MATCH(F45,Assumptions!$B$7:$B$12,0))) -> 261.0045 | S45: =IF(N45="Cancelled",Assumptions!$C$19,IF(N45="Returned",Assumptions!$C$17+O45*Assumptions!$C$18+Assumptions!$C$20,Assumptions!$C$17+O45*Assumptions!$C$18)) -> 41.8 | T45: =R45+S45 -> 302.8045 | U45: =K45-T45 -> 268.2045 | V45: =IF(U45>0,U45,0) -> 268.2045 | W45: =IF(U45>0,U45/H45,0) -> 0.46241358 | X45: =IF(U45<0,-U45,0) -> 0 | Y45: =IF(U45<0,-U45/H45,0) -> 0 | Z45: =IF(U45>=0,"Profitable",IF(N45="Cancelled","Order Cancelled",IF(N45="Returned","Order Returned",IF(AND(I45>=0.15,U45<0),"High Discount",IF(S45>H45,"Delivery Cost Exceeded Order Value","Low Order Value / Thin Margin"))))) -> Profitable
A46: ORD10215 | B46: 46058.592 | C46: Kritika Menon | D46: Delhi | E46: Website | F46: Food & Beverage | G46: 2 | H46: 604.6 | I46: 0.2 | J46: 29 | K46: =IF(N46="Cancelled",0,IF(N46="Returned",J46,H46*(1-I46)+J46)) -> 512.68 | L46: Net Banking | M46: Sunil Barik | N46: Delivered | O46: 63 | P46: 4 | Q46: =TEXT(tblOrders[[#This Row],[Order Date]],"mmm-yyyy") -> Feb-2026 | R46: =IF(N46="Cancelled",0,H46*INDEX(Assumptions!$C$7:$C$12,MATCH(F46,Assumptions!$B$7:$B$12,0))) -> 272.07 | S46: =IF(N46="Cancelled",Assumptions!$C$19,IF(N46="Returned",Assumptions!$C$17+O46*Assumptions!$C$18+Assumptions!$C$20,Assumptions!$C$17+O46*Assumptions!$C$18)) -> 43.9 | T46: =R46+S46 -> 315.97 | U46: =K46-T46 -> 196.71 | V46: =IF(U46>0,U46,0) -> 196.71 | W46: =IF(U46>0,U46/H46,0) -> 0.32535561 | X46: =IF(U46<0,-U46,0) -> 0 | Y46: =IF(U46<0,-U46/H46,0) -> 0 | Z46: =IF(U46>=0,"Profitable",IF(N46="Cancelled","Order Cancelled",IF(N46="Returned","Order Returned",IF(AND(I46>=0.15,U46<0),"High Discount",IF(S46>H46,"Delivery Cost Exceeded Order Value","Low Order Value / Thin Margin"))))) -> Profitable
A47: ORD10127 | B47: 46058.806 | C47: Meera Kapoor | D47: Chennai | E47: Mobile App | F47: Pharmacy | G47: 2 | H47: 940.89 | I47: 0.1 | J47: 39 | K47: =IF(N47="Cancelled",0,IF(N47="Returned",J47,H47*(1-I47)+J47)) -> 0 | L47: Cash on Delivery | M47: Kunal Mehta | N47: Cancelled | Q47: =TEXT(tblOrders[[#This Row],[Order Date]],"mmm-yyyy") -> Feb-2026 | R47: =IF(N47="Cancelled",0,H47*INDEX(Assumptions!$C$7:$C$12,MATCH(F47,Assumptions!$B$7:$B$12,0))) -> 0 | S47: =IF(N47="Cancelled",Assumptions!$C$19,IF(N47="Returned",Assumptions!$C$17+O47*Assumptions!$C$18+Assumptions!$C$20,Assumptions!$C$17+O47*Assumptions!$C$18)) -> 15 | T47: =R47+S47 -> 15 | U47: =K47-T47 -> -15 | V47: =IF(U47>0,U47,0) -> 0 | W47: =IF(U47>0,U47/H47,0) -> 0 | X47: =IF(U47<0,-U47,0) -> 15 | Y47: =IF(U47<0,-U47/H47,0) -> 0.015942352 | Z47: =IF(U47>=0,"Profitable",IF(N47="Cancelled","Order Cancelled",IF(N47="Returned","Order Returned",IF(AND(I47>=0.15,U47<0),"High Discount",IF(S47>H47,"Delivery Cost Exceeded Order Value","Low Order Value / Thin Margin"))))) -> Order Cancelled
A48: ORD10086 | B48: 46058.844 | C48: Varun Bose | D48: Pune | E48: Mobile App | F48: Electronics | G48: 4 | H48: 11407.6 | I48: 0 | J48: 0 | K48: =IF(N48="Cancelled",0,IF(N48="Returned",J48,H48*(1-I48)+J48)) -> 11407.6 | L48: Credit/Debit Card | M48: Sunil Barik | N48: Delivered | O48: 47 | P48: 5 | Q48: =TEXT(tblOrders[[#This Row],[Order Date]],"mmm-yyyy") -> Feb-2026 | R48: =IF(N48="Cancelled",0,H48*INDEX(Assumptions!$C$7:$C$12,MATCH(F48,Assumptions!$B$7:$B$12,0))) -> 10038.688 | S48: =IF(N48="Cancelled",Assumptions!$C$19,IF(N48="Returned",Assumptions!$C$17+O48*Assumptions!$C$18+Assumptions!$C$20,Assumptions!$C$17+O48*Assumptions!$C$18)) -> 39.1 | T48: =R48+S48 -> 10077.788 | U48: =K48-T48 -> 1329.812 | V48: =IF(U48>0,U48,0) -> 1329.812 | W48: =IF(U48>0,U48/H48,0) -> 0.11657246 | X48: =IF(U48<0,-U48,0) -> 0 | Y48: =IF(U48<0,-U48/H48,0) -> 0 | Z48: =IF(U48>=0,"Profitable",IF(N48="Cancelled","Order Cancelled",IF(N48="Returned","Order Returned",IF(AND(I48>=0.15,U48<0),"High Discount",IF(S48>H48,"Delivery Cost Exceeded Order Value","Low Order Value / Thin Margin"))))) -> Profitable
A49: ORD10158 | B49: 46058.903 | C49: Aarav Sharma | D49: Mumbai | E49: Website | F49: Grocery | G49: 1 | H49: 379.66 | I49: 0.05 | J49: 49 | K49: =IF(N49="Cancelled",0,IF(N49="Returned",J49,H49*(1-I49)+J49)) -> 409.677 | L49: UPI/Wallet | M49: Pankaj Dey | N49: Delivered | O49: 79 | P49: 5 | Q49: =TEXT(tblOrders[[#This Row],[Order Date]],"mmm-yyyy") -> Feb-2026 | R49: =IF(N49="Cancelled",0,H49*INDEX(Assumptions!$C$7:$C$12,MATCH(F49,Assumptions!$B$7:$B$12,0))) -> 296.1348 | S49: =IF(N49="Cancelled",Assumptions!$C$19,IF(N49="Returned",Assumptions!$C$17+O49*Assumptions!$C$18+Assumptions!$C$20,Assumptions!$C$17+O49*Assumptions!$C$18)) -> 48.7 | T49: =R49+S49 -> 344.8348 | U49: =K49-T49 -> 64.8422 | V49: =IF(U49>0,U49,0) -> 64.8422 | W49: =IF(U49>0,U49/H49,0) -> 0.17079018 | X49: =IF(U49<0,-U49,0) -> 0 | Y49: =IF(U49<0,-U49/H49,0) -> 0 | Z49: =IF(U49>=0,"Profitable",IF(N49="Cancelled","Order Cancelled",IF(N49="Returned","Order Returned",IF(AND(I49>=0.15,U49<0),"High Discount",IF(S49>H49,"Delivery Cost Exceeded Order Value","Low Order Value / Thin Margin"))))) -> Profitable
A50: ORD10083 | B50: 46059.819 | C50: Aryan Agarwal | D50: Pune | E50: Mobile App | F50: Home & Living | G50: 5 | H50: 1447.77 | I50: 0.05 | J50: 0 | K50: =IF(N50="Cancelled",0,IF(N50="Returned",J50,H50*(1-I50)+J50)) -> 1375.3815 | L50: Net Banking | M50: Kunal Mehta | N50: Delivered | O50: 65 | P50: 4 | Q50: =TEXT(tblOrders[[#This Row],[Order Date]],"mmm-yyyy") -> Feb-2026 | R50: =IF(N50="Cancelled",0,H50*INDEX(Assumptions!$C$7:$C$12,MATCH(F50,Assumptions!$B$7:$B$12,0))) -> 941.0505 | S50: =IF(N50="Cancelled",Assumptions!$C$19,IF(N50="Returned",Assumptions!$C$17+O50*Assumptions!$C$18+Assumptions!$C$20,Assumptions!$C$17+O50*Assumptions!$C$18)) -> 44.5 | T50: =R50+S50 -> 985.5505 | U50: =K50-T50 -> 389.831 | V50: =IF(U50>0,U50,0) -> 389.831 | W50: =IF(U50>0,U50/H50,0) -> 0.26926307 | X50: =IF(U50<0,-U50,0) -> 0 | Y50: =IF(U50<0,-U50/H50,0) -> 0 | Z50: =IF(U50>=0,"Profitable",IF(N50="Cancelled","Order Cancelled",IF(N50="Returned","Order Returned",IF(AND(I50>=0.15,U50<0),"High Discount",IF(S50>H50,"Delivery Cost Exceeded Order Value","Low Order Value / Thin Margin"))))) -> Profitable
A51: ORD10058 | B51: 46061.649 | C51: Sneha Chatterjee | D51: Bhubaneswar | E51: Mobile App | F51: Fashion | G51: 5 | H51: 1695.68 | I51: 0 | J51: 0 | K51: =IF(N51="Cancelled",0,IF(N51="Returned",J51,H51*(1-I51)+J51)) -> 0 | L51: Credit/Debit Card | M51: Manoj Tiwari | N51: Returned | O51: 48 | P51: 3 | Q51: =TEXT(tblOrders[[#This Row],[Order Date]],"mmm-yyyy") -> Feb-2026 | R51: =IF(N51="Cancelled",0,H51*INDEX(Assumptions!$C$7:$C$12,MATCH(F51,Assumptions!$B$7:$B$12,0))) -> 932.624 | S51: =IF(N51="Cancelled",Assumptions!$C$19,IF(N51="Returned",Assumptions!$C$17+O51*Assumptions!$C$18+Assumptions!$C$20,Assumptions!$C$17+O51*Assumptions!$C$18)) -> 59.4 | T51: =R51+S51 -> 992.024 | U51: =K51-T51 -> -992.024 | V51: =IF(U51>0,U51,0) -> 0 | W51: =IF(U51>0,U51/H51,0) -> 0 | X51: =IF(U51<0,-U51,0) -> 992.024 | Y51: =IF(U51<0,-U51/H51,0) -> 0.58503019 | Z51: =IF(U51>=0,"Profitable",IF(N51="Cancelled","Order Cancelled",IF(N51="Returned","Order Returned",IF(AND(I51>=0.15,U51<0),"High Discount",IF(S51>H51,"Delivery Cost Exceeded Order Value","Low Order Value / Thin Margin"))))) -> Order Returned
A52: ORD10047 | B52: 46061.858 | C52: Priya Agarwal | D52: Mumbai | E52: Mobile App | F52: Home & Living | G52: 2 | H52: 887.02 | I52: 0.2 | J52: 59 | K52: =IF(N52="Cancelled",0,IF(N52="Returned",J52,H52*(1-I52)+J52)) -> 768.616 | L52: Credit/Debit Card | M52: Omkar Naik | N52: Delivered | O52: 66 | P52: 4 | Q52: =TEXT(tblOrders[[#This Row],[Order Date]],"mmm-yyyy") -> Feb-2026 | R52: =IF(N52="Cancelled",0,H52*INDEX(Assumptions!$C$7:$C$12,MATCH(F52,Assumptions!$B$7:$B$12,0))) -> 576.563 | S52: =IF(N52="Cancelled",Assumptions!$C$19,IF(N52="Returned",Assumptions!$C$17+O52*Assumptions!$C$18+Assumptions!$C$20,Assumptions!$C$17+O52*Assumptions!$C$18)) -> 44.8 | T52: =R52+S52 -> 621.363 | U52: =K52-T52 -> 147.253 | V52: =IF(U52>0,U52,0) -> 147.253 | W52: =IF(U52>0,U52/H52,0) -> 0.16600866 | X52: =IF(U52<0,-U52,0) -> 0 | Y52: =IF(U52<0,-U52/H52,0) -> 0 | Z52: =IF(U52>=0,"Profitable",IF(N52="Cancelled","Order Cancelled",IF(N52="Returned","Order Returned",IF(AND(I52>=0.15,U52<0),"High Discount",IF(S52>H52,"Delivery Cost Exceeded Order Value","Low Order Value / Thin Margin"))))) -> Profitable
A53: ORD10005 | B53: 46062.575 | C53: Sneha Verma | D53: Hyderabad | E53: Website | F53: Grocery | G53: 5 | H53: 1114.42 | I53: 0.1 | J53: 0 | K53: =IF(N53="Cancelled",0,IF(N53="Returned",J53,H53*(1-I53)+J53)) -> 1002.978 | L53: Cash on Delivery | M53: Jyoti Panda | N53: Delivered | O53: 32 | P53: 4 | Q53: =TEXT(tblOrders[[#This Row],[Order Date]],"mmm-yyyy") -> Feb-2026 | R53: =IF(N53="Cancelled",0,H53*INDEX(Assumptions!$C$7:$C$12,MATCH(F53,Assumptions!$B$7:$B$12,0))) -> 869.2476 | S53: =IF(N53="Cancelled",Assumptions!$C$19,IF(N53="Returned",Assumptions!$C$17+O53*Assumptions!$C$18+Assumptions!$C$20,Assumptions!$C$17+O53*Assumptions!$C$18)) -> 34.6 | T53: =R53+S53 -> 903.8476 | U53: =K53-T53 -> 99.1304 | V53: =IF(U53>0,U53,0) -> 99.1304 | W53: =IF(U53>0,U53/H53,0) -> 0.08895246 | X53: =IF(U53<0,-U53,0) -> 0 | Y53: =IF(U53<0,-U53/H53,0) -> 0 | Z53: =IF(U53>=0,"Profitable",IF(N53="Cancelled","Order Cancelled",IF(N53="Returned","Order Returned",IF(AND(I53>=0.15,U53<0),"High Discount",IF(S53>H53,"Delivery Cost Exceeded Order Value","Low Order Value / Thin Margin"))))) -> Profitable
A54: ORD10003 | B54: 46062.757 | C54: Tanya Pillai | D54: Chennai | E54: Mobile App | F54: Food & Beverage | G54: 1 | H54: 407.81 | I54: 0.1 | J54: 59 | K54: =IF(N54="Cancelled",0,IF(N54="Returned",J54,H54*(1-I54)+J54)) -> 59 | L54: Cash on Delivery | M54: Bikash Mallick | N54: Returned | O54: 19 | P54: 3 | Q54: =TEXT(tblOrders[[#This Row],[Order Date]],"mmm-yyyy") -> Feb-2026 | R54: =IF(N54="Cancelled",0,H54*INDEX(Assumptions!$C$7:$C$12,MATCH(F54,Assumptions!$B$7:$B$12,0))) -> 183.5145 | S54: =IF(N54="Cancelled",Assumptions!$C$19,IF(N54="Returned",Assumptions!$C$17+O54*Assumptions!$C$18+Assumptions!$C$20,Assumptions!$C$17+O54*Assumptions!$C$18)) -> 50.7 | T54: =R54+S54 -> 234.2145 | U54: =K54-T54 -> -175.2145 | V54: =IF(U54>0,U54,0) -> 0 | W54: =IF(U54>0,U54/H54,0) -> 0 | X54: =IF(U54<0,-U54,0) -> 175.2145 | Y54: =IF(U54<0,-U54/H54,0) -> 0.42964738 | Z54: =IF(U54>=0,"Profitable",IF(N54="Cancelled","Order Cancelled",IF(N54="Returned","Order Returned",IF(AND(I54>=0.15,U54<0),"High Discount",IF(S54>H54,"Delivery Cost Exceeded Order Value","Low Order Value / Thin Margin"))))) -> Order Returned
A55: ORD10081 | B55: 46062.771 | C55: Tanya Pillai | D55: Bhubaneswar | E55: Mobile App | F55: Grocery | G55: 5 | H55: 535.94 | I55: 0.2 | J55: 49 | K55: =IF(N55="Cancelled",0,IF(N55="Returned",J55,H55*(1-I55)+J55)) -> 477.752 | L55: Credit/Debit Card | M55: Usha Rani | N55: Delivered | O55: 89 | P55: 5 | Q55: =TEXT(tblOrders[[#This Row],[Order Date]],"mmm-yyyy") -> Feb-2026 | R55: =IF(N55="Cancelled",0,H55*INDEX(Assumptions!$C$7:$C$12,MATCH(F55,Assumptions!$B$7:$B$12,0))) -> 418.0332 | S55: =IF(N55="Cancelled",Assumptions!$C$19,IF(N55="Returned",Assumptions!$C$17+O55*Assumptions!$C$18+Assumptions!$C$20,Assumptions!$C$17+O55*Assumptions!$C$18)) -> 51.7 | T55: =R55+S55 -> 469.7332 | U55: =K55-T55 -> 8.0188 | V55: =IF(U55>0,U55,0) -> 8.0188 | W55: =IF(U55>0,U55/H55,0) -> 0.014962123 | X55: =IF(U55<0,-U55,0) -> 0 | Y55: =IF(U55<0,-U55/H55,0) -> 0 | Z55: =IF(U55>=0,"Profitable",IF(N55="Cancelled","Order Cancelled",IF(N55="Returned","Order Returned",IF(AND(I55>=0.15,U55<0),"High Discount",IF(S55>H55,"Delivery Cost Exceeded Order Value","Low Order Value / Thin Margin"))))) -> Profitable
A56: ORD10049 | B56: 46063.351 | C56: Tanya Das | D56: Mumbai | E56: Mobile App | F56: Fashion | G56: 3 | H56: 420.77 | I56: 0 | J56: 49 | K56: =IF(N56="Cancelled",0,IF(N56="Returned",J56,H56*(1-I56)+J56)) -> 469.77 | L56: Net Banking | M56: Tarun Chauhan | N56: Delivered | O56: 47 | P56: 4 | Q56: =TEXT(tblOrders[[#This Row],[Order Date]],"mmm-yyyy") -> Feb-2026 | R56: =IF(N56="Cancelled",0,H56*INDEX(Assumptions!$C$7:$C$12,MATCH(F56,Assumptions!$B$7:$B$12,0))) -> 231.4235 | S56: =IF(N56="Cancelled",Assumptions!$C$19,IF(N56="Returned",Assumptions!$C$17+O56*Assumptions!$C$18+Assumptions!$C$20,Assumptions!$C$17+O56*Assumptions!$C$18)) -> 39.1 | T56: =R56+S56 -> 270.5235 | U56: =K56-T56 -> 199.2465 | V56: =IF(U56>0,U56,0) -> 199.2465 | W56: =IF(U56>0,U56/H56,0) -> 0.47352829 | X56: =IF(U56<0,-U56,0) -> 0 | Y56: =IF(U56<0,-U56/H56,0) -> 0 | Z56: =IF(U56>=0,"Profitable",IF(N56="Cancelled","Order Cancelled",IF(N56="Returned","Order Returned",IF(AND(I56>=0.15,U56<0),"High Discount",IF(S56>H56,"Delivery Cost Exceeded Order Value","Low Order Value / Thin Margin"))))) -> Profitable
A57: ORD10217 | B57: 46063.385 | C57: Meera Iyer | D57: Delhi | E57: Mobile App | F57: Food & Beverage | G57: 6 | H57: 144.73 | I57: 0 | J57: 59 | K57: =IF(N57="Cancelled",0,IF(N57="Returned",J57,H57*(1-I57)+J57)) -> 0 | L57: Cash on Delivery | M57: Farhan Ali | N57: Cancelled | Q57: =TEXT(tblOrders[[#This Row],[Order Date]],"mmm-yyyy") -> Feb-2026 | R57: =IF(N57="Cancelled",0,H57*INDEX(Assumptions!$C$7:$C$12,MATCH(F57,Assumptions!$B$7:$B$12,0))) -> 0 | S57: =IF(N57="Cancelled",Assumptions!$C$19,IF(N57="Returned",Assumptions!$C$17+O57*Assumptions!$C$18+Assumptions!$C$20,Assumptions!$C$17+O57*Assumptions!$C$18)) -> 15 | T57: =R57+S57 -> 15 | U57: =K57-T57 -> -15 | V57: =IF(U57>0,U57,0) -> 0 | W57: =IF(U57>0,U57/H57,0) -> 0 | X57: =IF(U57<0,-U57,0) -> 15 | Y57: =IF(U57<0,-U57/H57,0) -> 0.10364126 | Z57: =IF(U57>=0,"Profitable",IF(N57="Cancelled","Order Cancelled",IF(N57="Returned","Order Returned",IF(AND(I57>=0.15,U57<0),"High Discount",IF(S57>H57,"Delivery Cost Exceeded Order Value","Low Order Value / Thin Margin"))))) -> Order Cancelled
A58: ORD10030 | B58: 46063.83 | C58: Nikhil Singh | D58: Hyderabad | E58: Mobile App | F58: Fashion | G58: 2 | H58: 3407.49 | I58: 0 | J58: 0 | K58: =IF(N58="Cancelled",0,IF(N58="Returned",J58,H58*(1-I58)+J58)) -> 3407.49 | L58: Net Banking | M58: Anita Behera | N58: Delivered | O58: 53 | P58: 4 | Q58: =TEXT(tblOrders[[#This Row],[Order Date]],"mmm-yyyy") -> Feb-2026 | R58: =IF(N58="Cancelled",0,H58*INDEX(Assumptions!$C$7:$C$12,MATCH(F58,Assumptions!$B$7:$B$12,0))) -> 1874.1195 | S58: =IF(N58="Cancelled",Assumptions!$C$19,IF(N58="Returned",Assumptions!$C$17+O58*Assumptions!$C$18+Assumptions!$C$20,Assumptions!$C$17+O58*Assumptions!$C$18)) -> 40.9 | T58: =R58+S58 -> 1915.0195 | U58: =K58-T58 -> 1492.4705 | V58: =IF(U58>0,U58,0) -> 1492.4705 | W58: =IF(U58>0,U58/H58,0) -> 0.43799703 | X58: =IF(U58<0,-U58,0) -> 0 | Y58: =IF(U58<0,-U58/H58,0) -> 0 | Z58: =IF(U58>=0,"Profitable",IF(N58="Cancelled","Order Cancelled",IF(N58="Returned","Order Returned",IF(AND(I58>=0.15,U58<0),"High Discount",IF(S58>H58,"Delivery Cost Exceeded Order Value","Low Order Value / Thin Margin"))))) -> Profitable
A59: ORD10118 | B59: 46064.583 | C59: Dev Singh | D59: Pune | E59: Mobile App | F59: Food & Beverage | G59: 5 | H59: 815.94 | I59: 0.2 | J59: 29 | K59: =IF(N59="Cancelled",0,IF(N59="Returned",J59,H59*(1-I59)+J59)) -> 681.752 | L59: Cash on Delivery | M59: Deepak Sahu | N59: Delivered | O59: 88 | P59: 4 | Q59: =TEXT(tblOrders[[#This Row],[Order Date]],"mmm-yyyy") -> Feb-2026 | R59: =IF(N59="Cancelled",0,H59*INDEX(Assumptions!$C$7:$C$12,MATCH(F59,Assumptions!$B$7:$B$12,0))) -> 367.173 | S59: =IF(N59="Cancelled",Assumptions!$C$19,IF(N59="Returned",Assumptions!$C$17+O59*Assumptions!$C$18+Assumptions!$C$20,Assumptions!$C$17+O59*Assumptions!$C$18)) -> 51.4 | T59: =R59+S59 -> 418.573 | U59: =K59-T59 -> 263.179 | V59: =IF(U59>0,U59,0) -> 263.179 | W59: =IF(U59>0,U59/H59,0) -> 0.322547 | X59: =IF(U59<0,-U59,0) -> 0 | Y59: =IF(U59<0,-U59/H59,0) -> 0 | Z59: =IF(U59>=0,"Profitable",IF(N59="Cancelled","Order Cancelled",IF(N59="Returned","Order Returned",IF(AND(I59>=0.15,U59<0),"High Discount",IF(S59>H59,"Delivery Cost Exceeded Order Value","Low Order Value / Thin Margin"))))) -> Profitable
A60: ORD10185 | B60: 46065.714 | C60: Arjun Joshi | D60: Pune | E60: Website | F60: Food & Beverage | G60: 1 | H60: 556.06 | I60: 0.1 | J60: 49 | K60: =IF(N60="Cancelled",0,IF(N60="Returned",J60,H60*(1-I60)+J60)) -> 549.454 | L60: Credit/Debit Card | M60: Tarun Chauhan | N60: Delivered | O60: 55 | P60: 4 | Q60: =TEXT(tblOrders[[#This Row],[Order Date]],"mmm-yyyy") -> Feb-2026 | R60: =IF(N60="Cancelled",0,H60*INDEX(Assumptions!$C$7:$C$12,MATCH(F60,Assumptions!$B$7:$B$12,0))) -> 250.227 | S60: =IF(N60="Cancelled",Assumptions!$C$19,IF(N60="Returned",Assumptions!$C$17+O60*Assumptions!$C$18+Assumptions!$C$20,Assumptions!$C$17+O60*Assumptions!$C$18)) -> 41.5 | T60: =R60+S60 -> 291.727 | U60: =K60-T60 -> 257.727 | V60: =IF(U60>0,U60,0) -> 257.727 | W60: =IF(U60>0,U60/H60,0) -> 0.46348775 | X60: =IF(U60<0,-U60,0) -> 0 | Y60: =IF(U60<0,-U60/H60,0) -> 0 | Z60: =IF(U60>=0,"Profitable",IF(N60="Cancelled","Order Cancelled",IF(N60="Returned","Order Returned",IF(AND(I60>=0.15,U60<0),"High Discount",IF(S60>H60,"Delivery Cost Exceeded Order Value","Low Order Value / Thin Margin"))))) -> Profitable
A61: ORD10157 | B61: 46066.449 | C61: Aryan Sharma | D61: Mumbai | E61: Mobile App | F61: Fashion | G61: 5 | H61: 3964.2 | I61: 0 | J61: 0 | K61: =IF(N61="Cancelled",0,IF(N61="Returned",J61,H61*(1-I61)+J61)) -> 3964.2 | L61: UPI/Wallet | M61: Ramesh Yadav | N61: Delivered | O61: 27 | P61: 5 | Q61: =TEXT(tblOrders[[#This Row],[Order Date]],"mmm-yyyy") -> Feb-2026 | R61: =IF(N61="Cancelled",0,H61*INDEX(Assumptions!$C$7:$C$12,MATCH(F61,Assumptions!$B$7:$B$12,0))) -> 2180.31 | S61: =IF(N61="Cancelled",Assumptions!$C$19,IF(N61="Returned",Assumptions!$C$17+O61*Assumptions!$C$18+Assumptions!$C$20,Assumptions!$C$17+O61*Assumptions!$C$18)) -> 33.1 | T61: =R61+S61 -> 2213.41 | U61: =K61-T61 -> 1750.79 | V61: =IF(U61>0,U61,0) -> 1750.79 | W61: =IF(U61>0,U61/H61,0) -> 0.44165027 | X61: =IF(U61<0,-U61,0) -> 0 | Y61: =IF(U61<0,-U61/H61,0) -> 0 | Z61: =IF(U61>=0,"Profitable",IF(N61="Cancelled","Order Cancelled",IF(N61="Returned","Order Returned",IF(AND(I61>=0.15,U61<0),"High Discount",IF(S61>H61,"Delivery Cost Exceeded Order Value","Low Order Value / Thin Margin"))))) -> Profitable
A62: ORD10088 | B62: 46066.86 | C62: Yash Singh | D62: Delhi | E62: Website | F62: Fashion | G62: 3 | H62: 626.08 | I62: 0.2 | J62: 29 | K62: =IF(N62="Cancelled",0,IF(N62="Returned",J62,H62*(1-I62)+J62)) -> 529.864 | L62: Credit/Debit Card | M62: Anita Behera | N62: Delivered | O62: 69 | P62: 5 | Q62: =TEXT(tblOrders[[#This Row],[Order Date]],"mmm-yyyy") -> Feb-2026 | R62: =IF(N62="Cancelled",0,H62*INDEX(Assumptions!$C$7:$C$12,MATCH(F62,Assumptions!$B$7:$B$12,0))) -> 344.344 | S62: =IF(N62="Cancelled",Assumptions!$C$19,IF(N62="Returned",Assumptions!$C$17+O62*Assumptions!$C$18+Assumptions!$C$20,Assumptions!$C$17+O62*Assumptions!$C$18)) -> 45.7 | T62: =R62+S62 -> 390.044 | U62: =K62-T62 -> 139.82 | V62: =IF(U62>0,U62,0) -> 139.82 | W62: =IF(U62>0,U62/H62,0) -> 0.22332609 | X62: =IF(U62<0,-U62,0) -> 0 | Y62: =IF(U62<0,-U62/H62,0) -> 0 | Z62: =IF(U62>=0,"Profitable",IF(N62="Cancelled","Order Cancelled",IF(N62="Returned","Order Returned",IF(AND(I62>=0.15,U62<0),"High Discount",IF(S62>H62,"Delivery Cost Exceeded Order Value","Low Order Value / Thin Margin"))))) -> Profitable
A63: ORD10090 | B63: 46067.715 | C63: Dev Ghosh | D63: Delhi | E63: Mobile App | F63: Food & Beverage | G63: 2 | H63: 861.03 | I63: 0.15 | J63: 59 | K63: =IF(N63="Cancelled",0,IF(N63="Returned",J63,H63*(1-I63)+J63)) -> 790.8755 | L63: Net Banking | M63: Tarun Chauhan | N63: Delivered | O63: 92 | P63: 4 | Q63: =TEXT(tblOrders[[#This Row],[Order Date]],"mmm-yyyy") -> Feb-2026 | R63: =IF(N63="Cancelled",0,H63*INDEX(Assumptions!$C$7:$C$12,MATCH(F63,Assumptions!$B$7:$B$12,0))) -> 387.4635 | S63: =IF(N63="Cancelled",Assumptions!$C$19,IF(N63="Returned",Assumptions!$C$17+O63*Assumptions!$C$18+Assumptions!$C$20,Assumptions!$C$17+O63*Assumptions!$C$18)) -> 52.6 | T63: =R63+S63 -> 440.0635 | U63: =K63-T63 -> 350.812 | V63: =IF(U63>0,U63,0) -> 350.812 | W63: =IF(U63>0,U63/H63,0) -> 0.40743296 | X63: =IF(U63<0,-U63,0) -> 0 | Y63: =IF(U63<0,-U63/H63,0) -> 0 | Z63: =IF(U63>=0,"Profitable",IF(N63="Cancelled","Order Cancelled",IF(N63="Returned","Order Returned",IF(AND(I63>=0.15,U63<0),"High Discount",IF(S63>H63,"Delivery Cost Exceeded Order Value","Low Order Value / Thin Margin"))))) -> Profitable
A64: ORD10139 | B64: 46067.746 | C64: Tara Iyer | D64: Bhubaneswar | E64: Mobile App | F64: Food & Beverage | G64: 4 | H64: 512.22 | I64: 0 | J64: 59 | K64: =IF(N64="Cancelled",0,IF(N64="Returned",J64,H64*(1-I64)+J64)) -> 571.22 | L64: UPI/Wallet | M64: Kunal Mehta | N64: Delivered | O64: 35 | P64: 4 | Q64: =TEXT(tblOrders[[#This Row],[Order Date]],"mmm-yyyy") -> Feb-2026 | R64: =IF(N64="Cancelled",0,H64*INDEX(Assumptions!$C$7:$C$12,MATCH(F64,Assumptions!$B$7:$B$12,0))) -> 230.499 | S64: =IF(N64="Cancelled",Assumptions!$C$19,IF(N64="Returned",Assumptions!$C$17+O64*Assumptions!$C$18+Assumptions!$C$20,Assumptions!$C$17+O64*Assumptions!$C$18)) -> 35.5 | T64: =R64+S64 -> 265.999 | U64: =K64-T64 -> 305.221 | V64: =IF(U64>0,U64,0) -> 305.221 | W64: =IF(U64>0,U64/H64,0) -> 0.59587872 | X64: =IF(U64<0,-U64,0) -> 0 | Y64: =IF(U64<0,-U64/H64,0) -> 0 | Z64: =IF(U64>=0,"Profitable",IF(N64="Cancelled","Order Cancelled",IF(N64="Returned","Order Returned",IF(AND(I64>=0.15,U64<0),"High Discount",IF(S64>H64,"Delivery Cost Exceeded Order Value","Low Order Value / Thin Margin"))))) -> Profitable
A65: ORD10097 | B65: 46069.473 | C65: Varun Joshi | D65: Bhubaneswar | E65: Mobile App | F65: Home & Living | G65: 2 | H65: 5999.86 | I65: 0 | J65: 0 | K65: =IF(N65="Cancelled",0,IF(N65="Returned",J65,H65*(1-I65)+J65)) -> 5999.86 | L65: UPI/Wallet | M65: Sunil Barik | N65: Delivered | O65: 30 | P65: 5 | Q65: =TEXT(tblOrders[[#This Row],[Order Date]],"mmm-yyyy") -> Feb-2026 | R65: =IF(N65="Cancelled",0,H65*INDEX(Assumptions!$C$7:$C$12,MATCH(F65,Assumptions!$B$7:$B$12,0))) -> 3899.909 | S65: =IF(N65="Cancelled",Assumptions!$C$19,IF(N65="Returned",Assumptions!$C$17+O65*Assumptions!$C$18+Assumptions!$C$20,Assumptions!$C$17+O65*Assumptions!$C$18)) -> 34 | T65: =R65+S65 -> 3933.909 | U65: =K65-T65 -> 2065.951 | V65: =IF(U65>0,U65,0) -> 2065.951 | W65: =IF(U65>0,U65/H65,0) -> 0.3443332 | X65: =IF(U65<0,-U65,0) -> 0 | Y65: =IF(U65<0,-U65/H65,0) -> 0 | Z65: =IF(U65>=0,"Profitable",IF(N65="Cancelled","Order Cancelled",IF(N65="Returned","Order Returned",IF(AND(I65>=0.15,U65<0),"High Discount",IF(S65>H65,"Delivery Cost Exceeded Order Value","Low Order Value / Thin Margin"))))) -> Profitable
A66: ORD10214 | B66: 46070.512 | C66: Aditi Mishra | D66: Mumbai | E66: Mobile App | F66: Fashion | G66: 5 | H66: 2590.95 | I66: 0 | J66: 0 | K66: =IF(N66="Cancelled",0,IF(N66="Returned",J66,H66*(1-I66)+J66)) -> 2590.95 | L66: Cash on Delivery | M66: Ramesh Yadav | N66: Delivered | O66: 88 | P66: 4 | Q66: =TEXT(tblOrders[[#This Row],[Order Date]],"mmm-yyyy") -> Feb-2026 | R66: =IF(N66="Cancelled",0,H66*INDEX(Assumptions!$C$7:$C$12,MATCH(F66,Assumptions!$B$7:$B$12,0))) -> 1425.0225 | S66: =IF(N66="Cancelled",Assumptions!$C$19,IF(N66="Returned",Assumptions!$C$17+O66*Assumptions!$C$18+Assumptions!$C$20,Assumptions!$C$17+O66*Assumptions!$C$18)) -> 51.4 | T66: =R66+S66 -> 1476.4225 | U66: =K66-T66 -> 1114.5275 | V66: =IF(U66>0,U66,0) -> 1114.5275 | W66: =IF(U66>0,U66/H66,0) -> 0.43016172 | X66: =IF(U66<0,-U66,0) -> 0 | Y66: =IF(U66<0,-U66/H66,0) -> 0 | Z66: =IF(U66>=0,"Profitable",IF(N66="Cancelled","Order Cancelled",IF(N66="Returned","Order Returned",IF(AND(I66>=0.15,U66<0),"High Discount",IF(S66>H66,"Delivery Cost Exceeded Order Value","Low Order Value / Thin Margin"))))) -> Profitable
A67: ORD10105 | B67: 46070.779 | C67: Neha Mishra | D67: Bhubaneswar | E67: Website | F67: Grocery | G67: 1 | H67: 1151.07 | I67: 0.1 | J67: 0 | K67: =IF(N67="Cancelled",0,IF(N67="Returned",J67,H67*(1-I67)+J67)) -> 1035.963 | L67: UPI/Wallet | M67: Manoj Tiwari | N67: Delivered | O67: 78 | P67: 3 | Q67: =TEXT(tblOrders[[#This Row],[Order Date]],"mmm-yyyy") -> Feb-2026 | R67: =IF(N67="Cancelled",0,H67*INDEX(Assumptions!$C$7:$C$12,MATCH(F67,Assumptions!$B$7:$B$12,0))) -> 897.8346 | S67: =IF(N67="Cancelled",Assumptions!$C$19,IF(N67="Returned",Assumptions!$C$17+O67*Assumptions!$C$18+Assumptions!$C$20,Assumptions!$C$17+O67*Assumptions!$C$18)) -> 48.4 | T67: =R67+S67 -> 946.2346 | U67: =K67-T67 -> 89.7284 | V67: =IF(U67>0,U67,0) -> 89.7284 | W67: =IF(U67>0,U67/H67,0) -> 0.077952166 | X67: =IF(U67<0,-U67,0) -> 0 | Y67: =IF(U67<0,-U67/H67,0) -> 0 | Z67: =IF(U67>=0,"Profitable",IF(N67="Cancelled","Order Cancelled",IF(N67="Returned","Order Returned",IF(AND(I67>=0.15,U67<0),"High Discount",IF(S67>H67,"Delivery Cost Exceeded Order Value","Low Order Value / Thin Margin"))))) -> Profitable
A68: ORD10130 | B68: 46071.353 | C68: Nikhil Nair | D68: Hyderabad | E68: Mobile App | F68: Electronics | G68: 6 | H68: 3695.26 | I68: 0.1 | J68: 0 | K68: =IF(N68="Cancelled",0,IF(N68="Returned",J68,H68*(1-I68)+J68)) -> 0 | L68: Net Banking | M68: Ramesh Yadav | N68: Cancelled | Q68: =TEXT(tblOrders[[#This Row],[Order Date]],"mmm-yyyy") -> Feb-2026 | R68: =IF(N68="Cancelled",0,H68*INDEX(Assumptions!$C$7:$C$12,MATCH(F68,Assumptions!$B$7:$B$12,0))) -> 0 | S68: =IF(N68="Cancelled",Assumptions!$C$19,IF(N68="Returned",Assumptions!$C$17+O68*Assumptions!$C$18+Assumptions!$C$20,Assumptions!$C$17+O68*Assumptions!$C$18)) -> 15 | T68: =R68+S68 -> 15 | U68: =K68-T68 -> -15 | V68: =IF(U68>0,U68,0) -> 0 | W68: =IF(U68>0,U68/H68,0) -> 0 | X68: =IF(U68<0,-U68,0) -> 15 | Y68: =IF(U68<0,-U68/H68,0) -> 0.0040592543 | Z68: =IF(U68>=0,"Profitable",IF(N68="Cancelled","Order Cancelled",IF(N68="Returned","Order Returned",IF(AND(I68>=0.15,U68<0),"High Discount",IF(S68>H68,"Delivery Cost Exceeded Order Value","Low Order Value / Thin Margin"))))) -> Order Cancelled
A69: ORD10057 | B69: 46071.943 | C69: Priya Singh | D69: Kolkata | E69: Website | F69: Fashion | G69: 1 | H69: 1322.12 | I69: 0.2 | J69: 0 | K69: =IF(N69="Cancelled",0,IF(N69="Returned",J69,H69*(1-I69)+J69)) -> 1057.696 | L69: Net Banking | M69: Suresh Kumar | N69: Delivered | O69: 82 | P69: 4 | Q69: =TEXT(tblOrders[[#This Row],[Order Date]],"mmm-yyyy") -> Feb-2026 | R69: =IF(N69="Cancelled",0,H69*INDEX(Assumptions!$C$7:$C$12,MATCH(F69,Assumptions!$B$7:$B$12,0))) -> 727.166 | S69: =IF(N69="Cancelled",Assumptions!$C$19,IF(N69="Returned",Assumptions!$C$17+O69*Assumptions!$C$18+Assumptions!$C$20,Assumptions!$C$17+O69*Assumptions!$C$18)) -> 49.6 | T69: =R69+S69 -> 776.766 | U69: =K69-T69 -> 280.93 | V69: =IF(U69>0,U69,0) -> 280.93 | W69: =IF(U69>0,U69/H69,0) -> 0.21248449 | X69: =IF(U69<0,-U69,0) -> 0 | Y69: =IF(U69<0,-U69/H69,0) -> 0 | Z69: =IF(U69>=0,"Profitable",IF(N69="Cancelled","Order Cancelled",IF(N69="Returned","Order Returned",IF(AND(I69>=0.15,U69<0),"High Discount",IF(S69>H69,"Delivery Cost Exceeded Order Value","Low Order Value / Thin Margin"))))) -> Profitable
A70: ORD10044 | B70: 46072.547 | C70: Isha Das | D70: Chennai | E70: Website | F70: Food & Beverage | G70: 6 | H70: 248.12 | I70: 0 | J70: 59 | K70: =IF(N70="Cancelled",0,IF(N70="Returned",J70,H70*(1-I70)+J70)) -> 307.12 | L70: Cash on Delivery | M70: Jyoti Panda | N70: Delivered | O70: 85 | P70: 5 | Q70: =TEXT(tblOrders[[#This Row],[Order Date]],"mmm-yyyy") -> Feb-2026 | R70: =IF(N70="Cancelled",0,H70*INDEX(Assumptions!$C$7:$C$12,MATCH(F70,Assumptions!$B$7:$B$12,0))) -> 111.654 | S70: =IF(N70="Cancelled",Assumptions!$C$19,IF(N70="Returned",Assumptions!$C$17+O70*Assumptions!$C$18+Assumptions!$C$20,Assumptions!$C$17+O70*Assumptions!$C$18)) -> 50.5 | T70: =R70+S70 -> 162.154 | U70: =K70-T70 -> 144.966 | V70: =IF(U70>0,U70,0) -> 144.966 | W70: =IF(U70>0,U70/H70,0) -> 0.58425762 | X70: =IF(U70<0,-U70,0) -> 0 | Y70: =IF(U70<0,-U70/H70,0) -> 0 | Z70: =IF(U70>=0,"Profitable",IF(N70="Cancelled","Order Cancelled",IF(N70="Returned","Order Returned",IF(AND(I70>=0.15,U70<0),"High Discount",IF(S70>H70,"Delivery Cost Exceeded Order Value","Low Order Value / Thin Margin"))))) -> Profitable
A71: ORD10209 | B71: 46074.451 | C71: Priya Malhotra | D71: Chennai | E71: Mobile App | F71: Food & Beverage | G71: 1 | H71: 231.5 | I71: 0.05 | J71: 49 | K71: =IF(N71="Cancelled",0,IF(N71="Returned",J71,H71*(1-I71)+J71)) -> 268.925 | L71: Net Banking | M71: Omkar Naik | N71: Delivered | O71: 63 | P71: 3 | Q71: =TEXT(tblOrders[[#This Row],[Order Date]],"mmm-yyyy") -> Feb-2026 | R71: =IF(N71="Cancelled",0,H71*INDEX(Assumptions!$C$7:$C$12,MATCH(F71,Assumptions!$B$7:$B$12,0))) -> 104.175 | S71: =IF(N71="Cancelled",Assumptions!$C$19,IF(N71="Returned",Assumptions!$C$17+O71*Assumptions!$C$18+Assumptions!$C$20,Assumptions!$C$17+O71*Assumptions!$C$18)) -> 43.9 | T71: =R71+S71 -> 148.075 | U71: =K71-T71 -> 120.85 | V71: =IF(U71>0,U71,0) -> 120.85 | W71: =IF(U71>0,U71/H71,0) -> 0.52203024 | X71: =IF(U71<0,-U71,0) -> 0 | Y71: =IF(U71<0,-U71/H71,0) -> 0 | Z71: =IF(U71>=0,"Profitable",IF(N71="Cancelled","Order Cancelled",IF(N71="Returned","Order Returned",IF(AND(I71>=0.15,U71<0),"High Discount",IF(S71>H71,"Delivery Cost Exceeded Order Value","Low Order Value / Thin Margin"))))) -> Profitable
A72: ORD10036 | B72: 46074.876 | C72: Riya Reddy | D72: Bengaluru | E72: Mobile App | F72: Food & Beverage | G72: 4 | H72: 635.57 | I72: 0.1 | J72: 39 | K72: =IF(N72="Cancelled",0,IF(N72="Returned",J72,H72*(1-I72)+J72)) -> 611.013 | L72: Net Banking | M72: Usha Rani | N72: Delivered | O72: 65 | P72: 3 | Q72: =TEXT(tblOrders[[#This Row],[Order Date]],"mmm-yyyy") -> Feb-2026 | R72: =IF(N72="Cancelled",0,H72*INDEX(Assumptions!$C$7:$C$12,MATCH(F72,Assumptions!$B$7:$B$12,0))) -> 286.0065 | S72: =IF(N72="Cancelled",Assumptions!$C$19,IF(N72="Returned",Assumptions!$C$17+O72*Assumptions!$C$18+Assumptions!$C$20,Assumptions!$C$17+O72*Assumptions!$C$18)) -> 44.5 | T72: =R72+S72 -> 330.5065 | U72: =K72-T72 -> 280.5065 | V72: =IF(U72>0,U72,0) -> 280.5065 | W72: =IF(U72>0,U72/H72,0) -> 0.44134635 | X72: =IF(U72<0,-U72,0) -> 0 | Y72: =IF(U72<0,-U72/H72,0) -> 0 | Z72: =IF(U72>=0,"Profitable",IF(N72="Cancelled","Order Cancelled",IF(N72="Returned","Order Returned",IF(AND(I72>=0.15,U72<0),"High Discount",IF(S72>H72,"Delivery Cost Exceeded Order Value","Low Order Value / Thin Margin"))))) -> Profitable
A73: ORD10134 | B73: 46074.899 | C73: Vivaan Reddy | D73: Mumbai | E73: Mobile App | F73: Electronics | G73: 3 | H73: 2749.28 | I73: 0.1 | J73: 0 | K73: =IF(N73="Cancelled",0,IF(N73="Returned",J73,H73*(1-I73)+J73)) -> 2474.352 | L73: Credit/Debit Card | M73: Harpreet Singh | N73: Delivered | O73: 85 | P73: 3 | Q73: =TEXT(tblOrders[[#This Row],[Order Date]],"mmm-yyyy") -> Feb-2026 | R73: =IF(N73="Cancelled",0,H73*INDEX(Assumptions!$C$7:$C$12,MATCH(F73,Assumptions!$B$7:$B$12,0))) -> 2419.3664 | S73: =IF(N73="Cancelled",Assumptions!$C$19,IF(N73="Returned",Assumptions!$C$17+O73*Assumptions!$C$18+Assumptions!$C$20,Assumptions!$C$17+O73*Assumptions!$C$18)) -> 50.5 | T73: =R73+S73 -> 2469.8664 | U73: =K73-T73 -> 4.4856 | V73: =IF(U73>0,U73,0) -> 4.4856 | W73: =IF(U73>0,U73/H73,0) -> 0.0016315544 | X73: =IF(U73<0,-U73,0) -> 0 | Y73: =IF(U73<0,-U73/H73,0) -> 0 | Z73: =IF(U73>=0,"Profitable",IF(N73="Cancelled","Order Cancelled",IF(N73="Returned","Order Returned",IF(AND(I73>=0.15,U73<0),"High Discount",IF(S73>H73,"Delivery Cost Exceeded Order Value","Low Order Value / Thin Margin"))))) -> Profitable
A74: ORD10022 | B74: 46074.915 | C74: Neha Joshi | D74: Mumbai | E74: Mobile App | F74: Fashion | G74: 2 | H74: 1124.82 | I74: 0.15 | J74: 0 | K74: =IF(N74="Cancelled",0,IF(N74="Returned",J74,H74*(1-I74)+J74)) -> 956.097 | L74: Credit/Debit Card | M74: Imran Khan | N74: Delivered | O74: 53 | P74: 3 | Q74: =TEXT(tblOrders[[#This Row],[Order Date]],"mmm-yyyy") -> Feb-2026 | R74: =IF(N74="Cancelled",0,H74*INDEX(Assumptions!$C$7:$C$12,MATCH(F74,Assumptions!$B$7:$B$12,0))) -> 618.651 | S74: =IF(N74="Cancelled",Assumptions!$C$19,IF(N74="Returned",Assumptions!$C$17+O74*Assumptions!$C$18+Assumptions!$C$20,Assumptions!$C$17+O74*Assumptions!$C$18)) -> 40.9 | T74: =R74+S74 -> 659.551 | U74: =K74-T74 -> 296.546 | V74: =IF(U74>0,U74,0) -> 296.546 | W74: =IF(U74>0,U74/H74,0) -> 0.26363863 | X74: =IF(U74<0,-U74,0) -> 0 | Y74: =IF(U74<0,-U74/H74,0) -> 0 | Z74: =IF(U74>=0,"Profitable",IF(N74="Cancelled","Order Cancelled",IF(N74="Returned","Order Returned",IF(AND(I74>=0.15,U74<0),"High Discount",IF(S74>H74,"Delivery Cost Exceeded Order Value","Low Order Value / Thin Margin"))))) -> Profitable
A75: ORD10032 | B75: 46075.893 | C75: Shreya Chatterjee | D75: Hyderabad | E75: Website | F75: Electronics | G75: 6 | H75: 1077.35 | I75: 0.2 | J75: 0 | K75: =IF(N75="Cancelled",0,IF(N75="Returned",J75,H75*(1-I75)+J75)) -> 861.88 | L75: Net Banking | M75: Manoj Tiwari | N75: Delivered | O75: 63 | P75: 4 | Q75: =TEXT(tblOrders[[#This Row],[Order Date]],"mmm-yyyy") -> Feb-2026 | R75: =IF(N75="Cancelled",0,H75*INDEX(Assumptions!$C$7:$C$12,MATCH(F75,Assumptions!$B$7:$B$12,0))) -> 948.068 | S75: =IF(N75="Cancelled",Assumptions!$C$19,IF(N75="Returned",Assumptions!$C$17+O75*Assumptions!$C$18+Assumptions!$C$20,Assumptions!$C$17+O75*Assumptions!$C$18)) -> 43.9 | T75: =R75+S75 -> 991.968 | U75: =K75-T75 -> -130.088 | V75: =IF(U75>0,U75,0) -> 0 | W75: =IF(U75>0,U75/H75,0) -> 0 | X75: =IF(U75<0,-U75,0) -> 130.088 | Y75: =IF(U75<0,-U75/H75,0) -> 0.12074813 | Z75: =IF(U75>=0,"Profitable",IF(N75="Cancelled","Order Cancelled",IF(N75="Returned","Order Returned",IF(AND(I75>=0.15,U75<0),"High Discount",IF(S75>H75,"Delivery Cost Exceeded Order Value","Low Order Value / Thin Margin"))))) -> High Discount
A76: ORD10145 | B76: 46078.711 | C76: Aryan Chatterjee | D76: Delhi | E76: Mobile App | F76: Grocery | G76: 1 | H76: 718.22 | I76: 0 | J76: 29 | K76: =IF(N76="Cancelled",0,IF(N76="Returned",J76,H76*(1-I76)+J76)) -> 747.22 | L76: Net Banking | M76: Deepak Sahu | N76: Delivered | O76: 70 | P76: 3 | Q76: =TEXT(tblOrders[[#This Row],[Order Date]],"mmm-yyyy") -> Feb-2026 | R76: =IF(N76="Cancelled",0,H76*INDEX(Assumptions!$C$7:$C$12,MATCH(F76,Assumptions!$B$7:$B$12,0))) -> 560.2116 | S76: =IF(N76="Cancelled",Assumptions!$C$19,IF(N76="Returned",Assumptions!$C$17+O76*Assumptions!$C$18+Assumptions!$C$20,Assumptions!$C$17+O76*Assumptions!$C$18)) -> 46 | T76: =R76+S76 -> 606.2116 | U76: =K76-T76 -> 141.0084 | V76: =IF(U76>0,U76,0) -> 141.0084 | W76: =IF(U76>0,U76/H76,0) -> 0.19633037 | X76: =IF(U76<0,-U76,0) -> 0 | Y76: =IF(U76<0,-U76/H76,0) -> 0 | Z76: =IF(U76>=0,"Profitable",IF(N76="Cancelled","Order Cancelled",IF(N76="Returned","Order Returned",IF(AND(I76>=0.15,U76<0),"High Discount",IF(S76>H76,"Delivery Cost Exceeded Order Value","Low Order Value / Thin Margin"))))) -> Profitable
A77: ORD10089 | B77: 46079.576 | C77: Rohan Mishra | D77: Hyderabad | E77: Mobile App | F77: Grocery | G77: 1 | H77: 707.14 | I77: 0 | J77: 49 | K77: =IF(N77="Cancelled",0,IF(N77="Returned",J77,H77*(1-I77)+J77)) -> 756.14 | L77: Cash on Delivery | M77: Bikash Mallick | N77: Delivered | O77: 36 | P77: 3 | Q77: =TEXT(tblOrders[[#This Row],[Order Date]],"mmm-yyyy") -> Feb-2026 | R77: =IF(N77="Cancelled",0,H77*INDEX(Assumptions!$C$7:$C$12,MATCH(F77,Assumptions!$B$7:$B$12,0))) -> 551.5692 | S77: =IF(N77="Cancelled",Assumptions!$C$19,IF(N77="Returned",Assumptions!$C$17+O77*Assumptions!$C$18+Assumptions!$C$20,Assumptions!$C$17+O77*Assumptions!$C$18)) -> 35.8 | T77: =R77+S77 -> 587.3692 | U77: =K77-T77 -> 168.7708 | V77: =IF(U77>0,U77,0) -> 168.7708 | W77: =IF(U77>0,U77/H77,0) -> 0.23866674 | X77: =IF(U77<0,-U77,0) -> 0 | Y77: =IF(U77<0,-U77/H77,0) -> 0 | Z77: =IF(U77>=0,"Profitable",IF(N77="Cancelled","Order Cancelled",IF(N77="Returned","Order Returned",IF(AND(I77>=0.15,U77<0),"High Discount",IF(S77>H77,"Delivery Cost Exceeded Order Value","Low Order Value / Thin Margin"))))) -> Profitable
A78: ORD10147 | B78: 46080.875 | C78: Rohan Mishra | D78: Hyderabad | E78: Website | F78: Food & Beverage | G78: 4 | H78: 638.8 | I78: 0.1 | J78: 59 | K78: =IF(N78="Cancelled",0,IF(N78="Returned",J78,H78*(1-I78)+J78)) -> 633.92 | L78: Net Banking | M78: Lalita Rout | N78: Delivered | O78: 49 | P78: 4 | Q78: =TEXT(tblOrders[[#This Row],[Order Date]],"mmm-yyyy") -> Feb-2026 | R78: =IF(N78="Cancelled",0,H78*INDEX(Assumptions!$C$7:$C$12,MATCH(F78,Assumptions!$B$7:$B$12,0))) -> 287.46 | S78: =IF(N78="Cancelled",Assumptions!$C$19,IF(N78="Returned",Assumptions!$C$17+O78*Assumptions!$C$18+Assumptions!$C$20,Assumptions!$C$17+O78*Assumptions!$C$18)) -> 39.7 | T78: =R78+S78 -> 327.16 | U78: =K78-T78 -> 306.76 | V78: =IF(U78>0,U78,0) -> 306.76 | W78: =IF(U78>0,U78/H78,0) -> 0.4802129 | X78: =IF(U78<0,-U78,0) -> 0 | Y78: =IF(U78<0,-U78/H78,0) -> 0 | Z78: =IF(U78>=0,"Profitable",IF(N78="Cancelled","Order Cancelled",IF(N78="Returned","Order Returned",IF(AND(I78>=0.15,U78<0),"High Discount",IF(S78>H78,"Delivery Cost Exceeded Order Value","Low Order Value / Thin Margin"))))) -> Profitable
A79: ORD10045 | B79: 46081.549 | C79: Isha Sharma | D79: Chennai | E79: Website | F79: Electronics | G79: 2 | H79: 4695.22 | I79: 0 | J79: 0 | K79: =IF(N79="Cancelled",0,IF(N79="Returned",J79,H79*(1-I79)+J79)) -> 4695.22 | L79: Cash on Delivery | M79: Pankaj Dey | N79: Delivered | O79: 34 | P79: 5 | Q79: =TEXT(tblOrders[[#This Row],[Order Date]],"mmm-yyyy") -> Feb-2026 | R79: =IF(N79="Cancelled",0,H79*INDEX(Assumptions!$C$7:$C$12,MATCH(F79,Assumptions!$B$7:$B$12,0))) -> 4131.7936 | S79: =IF(N79="Cancelled",Assumptions!$C$19,IF(N79="Returned",Assumptions!$C$17+O79*Assumptions!$C$18+Assumptions!$C$20,Assumptions!$C$17+O79*Assumptions!$C$18)) -> 35.2 | T79: =R79+S79 -> 4166.9936 | U79: =K79-T79 -> 528.2264 | V79: =IF(U79>0,U79,0) -> 528.2264 | W79: =IF(U79>0,U79/H79,0) -> 0.11250301 | X79: =IF(U79<0,-U79,0) -> 0 | Y79: =IF(U79<0,-U79/H79,0) -> 0 | Z79: =IF(U79>=0,"Profitable",IF(N79="Cancelled","Order Cancelled",IF(N79="Returned","Order Returned",IF(AND(I79>=0.15,U79<0),"High Discount",IF(S79>H79,"Delivery Cost Exceeded Order Value","Low Order Value / Thin Margin"))))) -> Profitable
A80: ORD10001 | B80: 46081.876 | C80: Rohan Mishra | D80: Bengaluru | E80: Mobile App | F80: Pharmacy | G80: 1 | H80: 379.6 | I80: 0.1 | J80: 49 | K80: =IF(N80="Cancelled",0,IF(N80="Returned",J80,H80*(1-I80)+J80)) -> 390.64 | L80: Credit/Debit Card | M80: Omkar Naik | N80: Delivered | O80: 68 | P80: 5 | Q80: =TEXT(tblOrders[[#This Row],[Order Date]],"mmm-yyyy") -> Feb-2026 | R80: =IF(N80="Cancelled",0,H80*INDEX(Assumptions!$C$7:$C$12,MATCH(F80,Assumptions!$B$7:$B$12,0))) -> 265.72 | S80: =IF(N80="Cancelled",Assumptions!$C$19,IF(N80="Returned",Assumptions!$C$17+O80*Assumptions!$C$18+Assumptions!$C$20,Assumptions!$C$17+O80*Assumptions!$C$18)) -> 45.4 | T80: =R80+S80 -> 311.12 | U80: =K80-T80 -> 79.52 | V80: =IF(U80>0,U80,0) -> 79.52 | W80: =IF(U80>0,U80/H80,0) -> 0.20948367 | X80: =IF(U80<0,-U80,0) -> 0 | Y80: =IF(U80<0,-U80/H80,0) -> 0 | Z80: =IF(U80>=0,"Profitable",IF(N80="Cancelled","Order Cancelled",IF(N80="Returned","Order Returned",IF(AND(I80>=0.15,U80<0),"High Discount",IF(S80>H80,"Delivery Cost Exceeded Order Value","Low Order Value / Thin Margin"))))) -> Profitable
... A83: ORD10075 | B83: 46083.722 | C83: Isha Malhotra | D83: Hyderabad | E83: Mobile App | F83: Grocery | G83: 2 | H83: 928.8 | I83: 0.1 | J83: 29 | K83: =IF(N83="Cancelled",0,IF(N83="Returned",J83,H83*(1-I83)+J83)) -> 864.92 | L83: UPI/Wallet | M83: Tarun Chauhan | N83: Delivered | O83: 64 | P83: 5 | Q83: =TEXT(tblOrders[[#This Row],[Order Date]],"mmm-yyyy") -> Mar-2026 | R83: =IF(N83="Cancelled",0,H83*INDEX(Assumptions!$C$7:$C$12,MATCH(F83,Assumptions!$B$7:$B$12,0))) -> 724.464 | S83: =IF(N83="Cancelled",Assumptions!$C$19,IF(N83="Returned",Assumptions!$C$17+O83*Assumptions!$C$18+Assumptions!$C$20,Assumptions!$C$17+O83*Assumptions!$C$18)) -> 44.2 | T83: =R83+S83 -> 768.664 | U83: =K83-T83 -> 96.256 | V83: =IF(U83>0,U83,0) -> 96.256 | W83: =IF(U83>0,U83/H83,0) -> 0.1036348 | X83: =IF(U83<0,-U83,0) -> 0 | Y83: =IF(U83<0,-U83/H83,0) -> 0 | Z83: =IF(U83>=0,"Profitable",IF(N83="Cancelled","Order Cancelled",IF(N83="Returned","Order Returned",IF(AND(I83>=0.15,U83<0),"High Discount",IF(S83>H83,"Delivery Cost Exceeded Order Value","Low Order Value / Thin Margin"))))) -> Profitable
A84: ORD10016 | B84: 46085.554 | C84: Ishaan Nair | D84: Chennai | E84: Website | F84: Grocery | G84: 6 | H84: 467.64 | I84: 0.2 | J84: 29 | K84: =IF(N84="Cancelled",0,IF(N84="Returned",J84,H84*(1-I84)+J84)) -> 0 | L84: Cash on Delivery | M84: Bikash Mallick | N84: Cancelled | Q84: =TEXT(tblOrders[[#This Row],[Order Date]],"mmm-yyyy") -> Mar-2026 | R84: =IF(N84="Cancelled",0,H84*INDEX(Assumptions!$C$7:$C$12,MATCH(F84,Assumptions!$B$7:$B$12,0))) -> 0 | S84: =IF(N84="Cancelled",Assumptions!$C$19,IF(N84="Returned",Assumptions!$C$17+O84*Assumptions!$C$18+Assumptions!$C$20,Assumptions!$C$17+O84*Assumptions!$C$18)) -> 15 | T84: =R84+S84 -> 15 | U84: =K84-T84 -> -15 | V84: =IF(U84>0,U84,0) -> 0 | W84: =IF(U84>0,U84/H84,0) -> 0 | X84: =IF(U84<0,-U84,0) -> 15 | Y84: =IF(U84<0,-U84/H84,0) -> 0.032075956 | Z84: =IF(U84>=0,"Profitable",IF(N84="Cancelled","Order Cancelled",IF(N84="Returned","Order Returned",IF(AND(I84>=0.15,U84<0),"High Discount",IF(S84>H84,"Delivery Cost Exceeded Order Value","Low Order Value / Thin Margin"))))) -> Order Cancelled
A85: ORD10154 | B85: 46085.818 | C85: Neha Joshi | D85: Kolkata | E85: Mobile App | F85: Food & Beverage | G85: 2 | H85: 541.66 | I85: 0.2 | J85: 49 | K85: =IF(N85="Cancelled",0,IF(N85="Returned",J85,H85*(1-I85)+J85)) -> 482.328 | L85: Net Banking | M85: Imran Khan | N85: Delivered | O85: 63 | P85: 4 | Q85: =TEXT(tblOrders[[#This Row],[Order Date]],"mmm-yyyy") -> Mar-2026 | R85: =IF(N85="Cancelled",0,H85*INDEX(Assumptions!$C$7:$C$12,MATCH(F85,Assumptions!$B$7:$B$12,0))) -> 243.747 | S85: =IF(N85="Cancelled",Assumptions!$C$19,IF(N85="Returned",Assumptions!$C$17+O85*Assumptions!$C$18+Assumptions!$C$20,Assumptions!$C$17+O85*Assumptions!$C$18)) -> 43.9 | T85: =R85+S85 -> 287.647 | U85: =K85-T85 -> 194.681 | V85: =IF(U85>0,U85,0) -> 194.681 | W85: =IF(U85>0,U85/H85,0) -> 0.3594155 | X85: =IF(U85<0,-U85,0) -> 0 | Y85: =IF(U85<0,-U85/H85,0) -> 0 | Z85: =IF(U85>=0,"Profitable",IF(N85="Cancelled","Order Cancelled",IF(N85="Returned","Order Returned",IF(AND(I85>=0.15,U85<0),"High Discount",IF(S85>H85,"Delivery Cost Exceeded Order Value","Low Order Value / Thin Margin"))))) -> Profitable
A86: ORD10009 | B86: 46085.854 | C86: Vivaan Kapoor | D86: Delhi | E86: Mobile App | F86: Pharmacy | G86: 1 | H86: 1015.76 | I86: 0 | J86: 0 | K86: =IF(N86="Cancelled",0,IF(N86="Returned",J86,H86*(1-I86)+J86)) -> 1015.76 | L86: Net Banking | M86: Bikash Mallick | N86: Delivered | O86: 24 | P86: 5 | Q86: =TEXT(tblOrders[[#This Row],[Order Date]],"mmm-yyyy") -> Mar-2026 | R86: =IF(N86="Cancelled",0,H86*INDEX(Assumptions!$C$7:$C$12,MATCH(F86,Assumptions!$B$7:$B$12,0))) -> 711.032 | S86: =IF(N86="Cancelled",Assumptions!$C$19,IF(N86="Returned",Assumptions!$C$17+O86*Assumptions!$C$18+Assumptions!$C$20,Assumptions!$C$17+O86*Assumptions!$C$18)) -> 32.2 | T86: =R86+S86 -> 743.232 | U86: =K86-T86 -> 272.528 | V86: =IF(U86>0,U86,0) -> 272.528 | W86: =IF(U86>0,U86/H86,0) -> 0.2682996 | X86: =IF(U86<0,-U86,0) -> 0 | Y86: =IF(U86<0,-U86/H86,0) -> 0 | Z86: =IF(U86>=0,"Profitable",IF(N86="Cancelled","Order Cancelled",IF(N86="Returned","Order Returned",IF(AND(I86>=0.15,U86<0),"High Discount",IF(S86>H86,"Delivery Cost Exceeded Order Value","Low Order Value / Thin Margin"))))) -> Profitable
A87: ORD10002 | B87: 46086.816 | C87: Aditi Verma | D87: Pune | E87: Website | F87: Fashion | G87: 4 | H87: 3621.94 | I87: 0.05 | J87: 0 | K87: =IF(N87="Cancelled",0,IF(N87="Returned",J87,H87*(1-I87)+J87)) -> 3440.843 | L87: Cash on Delivery | M87: Pankaj Dey | N87: Delivered | O87: 35 | P87: 5 | Q87: =TEXT(tblOrders[[#This Row],[Order Date]],"mmm-yyyy") -> Mar-2026 | R87: =IF(N87="Cancelled",0,H87*INDEX(Assumptions!$C$7:$C$12,MATCH(F87,Assumptions!$B$7:$B$12,0))) -> 1992.067 | S87: =IF(N87="Cancelled",Assumptions!$C$19,IF(N87="Returned",Assumptions!$C$17+O87*Assumptions!$C$18+Assumptions!$C$20,Assumptions!$C$17+O87*Assumptions!$C$18)) -> 35.5 | T87: =R87+S87 -> 2027.567 | U87: =K87-T87 -> 1413.276 | V87: =IF(U87>0,U87,0) -> 1413.276 | W87: =IF(U87>0,U87/H87,0) -> 0.39019862 | X87: =IF(U87<0,-U87,0) -> 0 | Y87: =IF(U87<0,-U87/H87,0) -> 0 | Z87: =IF(U87>=0,"Profitable",IF(N87="Cancelled","Order Cancelled",IF(N87="Returned","Order Returned",IF(AND(I87>=0.15,U87<0),"High Discount",IF(S87>H87,"Delivery Cost Exceeded Order Value","Low Order Value / Thin Margin"))))) -> Profitable
A88: ORD10123 | B88: 46086.915 | C88: Ananya Sharma | D88: Pune | E88: Mobile App | F88: Grocery | G88: 5 | H88: 907.18 | I88: 0 | J88: 39 | K88: =IF(N88="Cancelled",0,IF(N88="Returned",J88,H88*(1-I88)+J88)) -> 39 | L88: Net Banking | M88: Jyoti Panda | N88: Returned | O88: 77 | P88: 2 | Q88: =TEXT(tblOrders[[#This Row],[Order Date]],"mmm-yyyy") -> Mar-2026 | R88: =IF(N88="Cancelled",0,H88*INDEX(Assumptions!$C$7:$C$12,MATCH(F88,Assumptions!$B$7:$B$12,0))) -> 707.6004 | S88: =IF(N88="Cancelled",Assumptions!$C$19,IF(N88="Returned",Assumptions!$C$17+O88*Assumptions!$C$18+Assumptions!$C$20,Assumptions!$C$17+O88*Assumptions!$C$18)) -> 68.1 | T88: =R88+S88 -> 775.7004 | U88: =K88-T88 -> -736.7004 | V88: =IF(U88>0,U88,0) -> 0 | W88: =IF(U88>0,U88/H88,0) -> 0 | X88: =IF(U88<0,-U88,0) -> 736.7004 | Y88: =IF(U88<0,-U88/H88,0) -> 0.81207743 | Z88: =IF(U88>=0,"Profitable",IF(N88="Cancelled","Order Cancelled",IF(N88="Returned","Order Returned",IF(AND(I88>=0.15,U88<0),"High Discount",IF(S88>H88,"Delivery Cost Exceeded Order Value","Low Order Value / Thin Margin"))))) -> Order Returned
A89: ORD10064 | B89: 46088.75 | C89: Dev Chatterjee | D89: Chennai | E89: Mobile App | F89: Pharmacy | G89: 3 | H89: 1042.21 | I89: 0 | J89: 0 | K89: =IF(N89="Cancelled",0,IF(N89="Returned",J89,H89*(1-I89)+J89)) -> 1042.21 | L89: UPI/Wallet | M89: Jyoti Panda | N89: Delivered | O89: 62 | P89: 5 | Q89: =TEXT(tblOrders[[#This Row],[Order Date]],"mmm-yyyy") -> Mar-2026 | R89: =IF(N89="Cancelled",0,H89*INDEX(Assumptions!$C$7:$C$12,MATCH(F89,Assumptions!$B$7:$B$12,0))) -> 729.547 | S89: =IF(N89="Cancelled",Assumptions!$C$19,IF(N89="Returned",Assumptions!$C$17+O89*Assumptions!$C$18+Assumptions!$C$20,Assumptions!$C$17+O89*Assumptions!$C$18)) -> 43.6 | T89: =R89+S89 -> 773.147 | U89: =K89-T89 -> 269.063 | V89: =IF(U89>0,U89,0) -> 269.063 | W89: =IF(U89>0,U89/H89,0) -> 0.25816582 | X89: =IF(U89<0,-U89,0) -> 0 | Y89: =IF(U89<0,-U89/H89,0) -> 0 | Z89: =IF(U89>=0,"Profitable",IF(N89="Cancelled","Order Cancelled",IF(N89="Returned","Order Returned",IF(AND(I89>=0.15,U89<0),"High Discount",IF(S89>H89,"Delivery Cost Exceeded Order Value","Low Order Value / Thin Margin"))))) -> Profitable
A90: ORD10068 | B90: 46088.953 | C90: Shreya Kapoor | D90: Delhi | E90: Website | F90: Home & Living | G90: 3 | H90: 4530.04 | I90: 0 | J90: 0 | K90: =IF(N90="Cancelled",0,IF(N90="Returned",J90,H90*(1-I90)+J90)) -> 4530.04 | L90: UPI/Wallet | M90: Harpreet Singh | N90: Delivered | O90: 27 | P90: 3 | Q90: =TEXT(tblOrders[[#This Row],[Order Date]],"mmm-yyyy") -> Mar-2026 | R90: =IF(N90="Cancelled",0,H90*INDEX(Assumptions!$C$7:$C$12,MATCH(F90,Assumptions!$B$7:$B$12,0))) -> 2944.526 | S90: =IF(N90="Cancelled",Assumptions!$C$19,IF(N90="Returned",Assumptions!$C$17+O90*Assumptions!$C$18+Assumptions!$C$20,Assumptions!$C$17+O90*Assumptions!$C$18)) -> 33.1 | T90: =R90+S90 -> 2977.626 | U90: =K90-T90 -> 1552.414 | V90: =IF(U90>0,U90,0) -> 1552.414 | W90: =IF(U90>0,U90/H90,0) -> 0.34269322 | X90: =IF(U90<0,-U90,0) -> 0 | Y90: =IF(U90<0,-U90/H90,0) -> 0 | Z90: =IF(U90>=0,"Profitable",IF(N90="Cancelled","Order Cancelled",IF(N90="Returned","Order Returned",IF(AND(I90>=0.15,U90<0),"High Discount",IF(S90>H90,"Delivery Cost Exceeded Order Value","Low Order Value / Thin Margin"))))) -> Profitable
A91: ORD10140 | B91: 46089.594 | C91: Vivaan Reddy | D91: Kolkata | E91: Mobile App | F91: Fashion | G91: 3 | H91: 1417.2 | I91: 0.15 | J91: 0 | K91: =IF(N91="Cancelled",0,IF(N91="Returned",J91,H91*(1-I91)+J91)) -> 1204.62 | L91: UPI/Wallet | M91: Harpreet Singh | N91: Delivered | O91: 64 | P91: 5 | Q91: =TEXT(tblOrders[[#This Row],[Order Date]],"mmm-yyyy") -> Mar-2026 | R91: =IF(N91="Cancelled",0,H91*INDEX(Assumptions!$C$7:$C$12,MATCH(F91,Assumptions!$B$7:$B$12,0))) -> 779.46 | S91: =IF(N91="Cancelled",Assumptions!$C$19,IF(N91="Returned",Assumptions!$C$17+O91*Assumptions!$C$18+Assumptions!$C$20,Assumptions!$C$17+O91*Assumptions!$C$18)) -> 44.2 | T91: =R91+S91 -> 823.66 | U91: =K91-T91 -> 380.96 | V91: =IF(U91>0,U91,0) -> 380.96 | W91: =IF(U91>0,U91/H91,0) -> 0.26881174 | X91: =IF(U91<0,-U91,0) -> 0 | Y91: =IF(U91<0,-U91/H91,0) -> 0 | Z91: =IF(U91>=0,"Profitable",IF(N91="Cancelled","Order Cancelled",IF(N91="Returned","Order Returned",IF(AND(I91>=0.15,U91<0),"High Discount",IF(S91>H91,"Delivery Cost Exceeded Order Value","Low Order Value / Thin Margin"))))) -> Profitable
A92: ORD10129 | B92: 46090.785 | C92: Vivaan Agarwal | D92: Pune | E92: Mobile App | F92: Home & Living | G92: 2 | H92: 4384.12 | I92: 0.1 | J92: 0 | K92: =IF(N92="Cancelled",0,IF(N92="Returned",J92,H92*(1-I92)+J92)) -> 3945.708 | L92: Net Banking | M92: Harpreet Singh | N92: Delivered | O92: 66 | P92: 3 | Q92: =TEXT(tblOrders[[#This Row],[Order Date]],"mmm-yyyy") -> Mar-2026 | R92: =IF(N92="Cancelled",0,H92*INDEX(Assumptions!$C$7:$C$12,MATCH(F92,Assumptions!$B$7:$B$12,0))) -> 2849.678 | S92: =IF(N92="Cancelled",Assumptions!$C$19,IF(N92="Returned",Assumptions!$C$17+O92*Assumptions!$C$18+Assumptions!$C$20,Assumptions!$C$17+O92*Assumptions!$C$18)) -> 44.8 | T92: =R92+S92 -> 2894.478 | U92: =K92-T92 -> 1051.23 | V92: =IF(U92>0,U92,0) -> 1051.23 | W92: =IF(U92>0,U92/H92,0) -> 0.2397813 | X92: =IF(U92<0,-U92,0) -> 0 | Y92: =IF(U92<0,-U92/H92,0) -> 0 | Z92: =IF(U92>=0,"Profitable",IF(N92="Cancelled","Order Cancelled",IF(N92="Returned","Order Returned",IF(AND(I92>=0.15,U92<0),"High Discount",IF(S92>H92,"Delivery Cost Exceeded Order Value","Low Order Value / Thin Margin"))))) -> Profitable
A93: ORD10162 | B93: 46092.374 | C93: Aryan Kapoor | D93: Pune | E93: Website | F93: Grocery | G93: 5 | H93: 741.69 | I93: 0 | J93: 39 | K93: =IF(N93="Cancelled",0,IF(N93="Returned",J93,H93*(1-I93)+J93)) -> 780.69 | L93: Cash on Delivery | M93: Deepak Sahu | N93: Delivered | O93: 44 | P93: 5 | Q93: =TEXT(tblOrders[[#This Row],[Order Date]],"mmm-yyyy") -> Mar-2026 | R93: =IF(N93="Cancelled",0,H93*INDEX(Assumptions!$C$7:$C$12,MATCH(F93,Assumptions!$B$7:$B$12,0))) -> 578.5182 | S93: =IF(N93="Cancelled",Assumptions!$C$19,IF(N93="Returned",Assumptions!$C$17+O93*Assumptions!$C$18+Assumptions!$C$20,Assumptions!$C$17+O93*Assumptions!$C$18)) -> 38.2 | T93: =R93+S93 -> 616.7182 | U93: =K93-T93 -> 163.9718 | V93: =IF(U93>0,U93,0) -> 163.9718 | W93: =IF(U93>0,U93/H93,0) -> 0.22107862 | X93: =IF(U93<0,-U93,0) -> 0 | Y93: =IF(U93<0,-U93/H93,0) -> 0 | Z93: =IF(U93>=0,"Profitable",IF(N93="Cancelled","Order Cancelled",IF(N93="Returned","Order Returned",IF(AND(I93>=0.15,U93<0),"High Discount",IF(S93>H93,"Delivery Cost Exceeded Order Value","Low Order Value / Thin Margin"))))) -> Profitable
A94: ORD10031 | B94: 46092.556 | C94: Rahul Chatterjee | D94: Bhubaneswar | E94: Mobile App | F94: Pharmacy | G94: 2 | H94: 408.39 | I94: 0.15 | J94: 39 | K94: =IF(N94="Cancelled",0,IF(N94="Returned",J94,H94*(1-I94)+J94)) -> 386.1315 | L94: Credit/Debit Card | M94: Sunil Barik | N94: Delivered | O94: 70 | P94: 4 | Q94: =TEXT(tblOrders[[#This Row],[Order Date]],"mmm-yyyy") -> Mar-2026 | R94: =IF(N94="Cancelled",0,H94*INDEX(Assumptions!$C$7:$C$12,MATCH(F94,Assumptions!$B$7:$B$12,0))) -> 285.873 | S94: =IF(N94="Cancelled",Assumptions!$C$19,IF(N94="Returned",Assumptions!$C$17+O94*Assumptions!$C$18+Assumptions!$C$20,Assumptions!$C$17+O94*Assumptions!$C$18)) -> 46 | T94: =R94+S94 -> 331.873 | U94: =K94-T94 -> 54.2585 | V94: =IF(U94>0,U94,0) -> 54.2585 | W94: =IF(U94>0,U94/H94,0) -> 0.13285952 | X94: =IF(U94<0,-U94,0) -> 0 | Y94: =IF(U94<0,-U94/H94,0) -> 0 | Z94: =IF(U94>=0,"Profitable",IF(N94="Cancelled","Order Cancelled",IF(N94="Returned","Order Returned",IF(AND(I94>=0.15,U94<0),"High Discount",IF(S94>H94,"Delivery Cost Exceeded Order Value","Low Order Value / Thin Margin"))))) -> Profitable
A95: ORD10072 | B95: 46094.364 | C95: Arjun Das | D95: Pune | E95: Mobile App | F95: Electronics | G95: 2 | H95: 12947.39 | I95: 0 | J95: 0 | K95: =IF(N95="Cancelled",0,IF(N95="Returned",J95,H95*(1-I95)+J95)) -> 12947.39 | L95: Cash on Delivery | M95: Manoj Tiwari | N95: Delivered | O95: 63 | P95: 3 | Q95: =TEXT(tblOrders[[#This Row],[Order Date]],"mmm-yyyy") -> Mar-2026 | R95: =IF(N95="Cancelled",0,H95*INDEX(Assumptions!$C$7:$C$12,MATCH(F95,Assumptions!$B$7:$B$12,0))) -> 11393.703 | S95: =IF(N95="Cancelled",Assumptions!$C$19,IF(N95="Returned",Assumptions!$C$17+O95*Assumptions!$C$18+Assumptions!$C$20,Assumptions!$C$17+O95*Assumptions!$C$18)) -> 43.9 | T95: =R95+S95 -> 11437.603 | U95: =K95-T95 -> 1509.7868 | V95: =IF(U95>0,U95,0) -> 1509.7868 | W95: =IF(U95>0,U95/H95,0) -> 0.11660936 | X95: =IF(U95<0,-U95,0) -> 0 | Y95: =IF(U95<0,-U95/H95,0) -> 0 | Z95: =IF(U95>=0,"Profitable",IF(N95="Cancelled","Order Cancelled",IF(N95="Returned","Order Returned",IF(AND(I95>=0.15,U95<0),"High Discount",IF(S95>H95,"Delivery Cost Exceeded Order Value","Low Order Value / Thin Margin"))))) -> Profitable
A96: ORD10035 | B96: 46094.87 | C96: Aryan Sharma | D96: Hyderabad | E96: Website | F96: Fashion | G96: 4 | H96: 371.72 | I96: 0.1 | J96: 29 | K96: =IF(N96="Cancelled",0,IF(N96="Returned",J96,H96*(1-I96)+J96)) -> 363.548 | L96: Cash on Delivery | M96: Ramesh Yadav | N96: Delivered | O96: 26 | P96: 5 | Q96: =TEXT(tblOrders[[#This Row],[Order Date]],"mmm-yyyy") -> Mar-2026 | R96: =IF(N96="Cancelled",0,H96*INDEX(Assumptions!$C$7:$C$12,MATCH(F96,Assumptions!$B$7:$B$12,0))) -> 204.446 | S96: =IF(N96="Cancelled",Assumptions!$C$19,IF(N96="Returned",Assumptions!$C$17+O96*Assumptions!$C$18+Assumptions!$C$20,Assumptions!$C$17+O96*Assumptions!$C$18)) -> 32.8 | T96: =R96+S96 -> 237.246 | U96: =K96-T96 -> 126.302 | V96: =IF(U96>0,U96,0) -> 126.302 | W96: =IF(U96>0,U96/H96,0) -> 0.33977725 | X96: =IF(U96<0,-U96,0) -> 0 | Y96: =IF(U96<0,-U96/H96,0) -> 0 | Z96: =IF(U96>=0,"Profitable",IF(N96="Cancelled","Order Cancelled",IF(N96="Returned","Order Returned",IF(AND(I96>=0.15,U96<0),"High Discount",IF(S96>H96,"Delivery Cost Exceeded Order Value","Low Order Value / Thin Margin"))))) -> Profitable
... A99: ORD10027 | B99: 46095.696 | C99: Shreya Patel | D99: Kolkata | E99: Mobile App | F99: Food & Beverage | G99: 2 | H99: 638.24 | I99: 0 | J99: 39 | K99: =IF(N99="Cancelled",0,IF(N99="Returned",J99,H99*(1-I99)+J99)) -> 677.24 | L99: Credit/Debit Card | M99: Usha Rani | N99: Delivered | O99: 49 | P99: 4 | Q99: =TEXT(tblOrders[[#This Row],[Order Date]],"mmm-yyyy") -> Mar-2026 | R99: =IF(N99="Cancelled",0,H99*INDEX(Assumptions!$C$7:$C$12,MATCH(F99,Assumptions!$B$7:$B$12,0))) -> 287.208 | S99: =IF(N99="Cancelled",Assumptions!$C$19,IF(N99="Returned",Assumptions!$C$17+O99*Assumptions!$C$18+Assumptions!$C$20,Assumptions!$C$17+O99*Assumptions!$C$18)) -> 39.7 | T99: =R99+S99 -> 326.908 | U99: =K99-T99 -> 350.332 | V99: =IF(U99>0,U99,0) -> 350.332 | W99: =IF(U99>0,U99/H99,0) -> 0.54890323 | X99: =IF(U99<0,-U99,0) -> 0 | Y99: =IF(U99<0,-U99/H99,0) -> 0 | Z99: =IF(U99>=0,"Profitable",IF(N99="Cancelled","Order Cancelled",IF(N99="Returned","Order Returned",IF(AND(I99>=0.15,U99<0),"High Discount",IF(S99>H99,"Delivery Cost Exceeded Order Value","Low Order Value / Thin Margin"))))) -> Profitable
A100: ORD10136 | B100: 46096.752 | C100: Divya Gupta | D100: Bhubaneswar | E100: Mobile App | F100: Home & Living | G100: 5 | H100: 1546.88 | I100: 0.15 | J100: 0 | K100: =IF(N100="Cancelled",0,IF(N100="Returned",J100,H100*(1-I100)+J100)) -> 0 | L100: UPI/Wallet | M100: Farhan Ali | N100: Cancelled | Q100: =TEXT(tblOrders[[#This Row],[Order Date]],"mmm-yyyy") -> Mar-2026 | R100: =IF(N100="Cancelled",0,H100*INDEX(Assumptions!$C$7:$C$12,MATCH(F100,Assumptions!$B$7:$B$12,0))) -> 0 | S100: =IF(N100="Cancelled",Assumptions!$C$19,IF(N100="Returned",Assumptions!$C$17+O100*Assumptions!$C$18+Assumptions!$C$20,Assumptions!$C$17+O100*Assumptions!$C$18)) -> 15 | T100: =R100+S100 -> 15 | U100: =K100-T100 -> -15 | V100: =IF(U100>0,U100,0) -> 0 | W100: =IF(U100>0,U100/H100,0) -> 0 | X100: =IF(U100<0,-U100,0) -> 15 | Y100: =IF(U100<0,-U100/H100,0) -> 0.0096969384 | Z100: =IF(U100>=0,"Profitable",IF(N100="Cancelled","Order Cancelled",IF(N100="Returned","Order Returned",IF(AND(I100>=0.15,U100<0),"High Discount",IF(S100>H100,"Delivery Cost Exceeded Order Value","Low Order Value / Thin Margin"))))) -> Order Cancelled
A101: ORD10156 | B101: 46098.425 | C101: Rahul Gupta | D101: Delhi | E101: Mobile App | F101: Electronics | G101: 2 | H101: 7890.08 | I101: 0.15 | J101: 0 | K101: =IF(N101="Cancelled",0,IF(N101="Returned",J101,H101*(1-I101)+J101)) -> 6706.568 | L101: Cash on Delivery | M101: Pankaj Dey | N101: Delivered | O101: 80 | P101: 5 | Q101: =TEXT(tblOrders[[#This Row],[Order Date]],"mmm-yyyy") -> Mar-2026 | R101: =IF(N101="Cancelled",0,H101*INDEX(Assumptions!$C$7:$C$12,MATCH(F101,Assumptions!$B$7:$B$12,0))) -> 6943.2704 | S101: =IF(N101="Cancelled",Assumptions!$C$19,IF(N101="Returned",Assumptions!$C$17+O101*Assumptions!$C$18+Assumptions!$C$20,Assumptions!$C$17+O101*Assumptions!$C$18)) -> 49 | T101: =R101+S101 -> 6992.2704 | U101: =K101-T101 -> -285.7024 | V101: =IF(U101>0,U101,0) -> 0 | W101: =IF(U101>0,U101/H101,0) -> 0 | X101: =IF(U101<0,-U101,0) -> 285.7024 | Y101: =IF(U101<0,-U101/H101,0) -> 0.03621033 | Z101: =IF(U101>=0,"Profitable",IF(N101="Cancelled","Order Cancelled",IF(N101="Returned","Order Returned",IF(AND(I101>=0.15,U101<0),"High Discount",IF(S101>H101,"Delivery Cost Exceeded Order Value","Low Order Value / Thin Margin"))))) -> High Discount
A102: ORD10163 | B102: 46099.442 | C102: Sahil Bose | D102: Bhubaneswar | E102: Website | F102: Grocery | G102: 4 | H102: 860.89 | I102: 0.1 | J102: 49 | K102: =IF(N102="Cancelled",0,IF(N102="Returned",J102,H102*(1-I102)+J102)) -> 823.801 | L102: Net Banking | M102: Anita Behera | N102: Delivered | O102: 35 | P102: 5 | Q102: =TEXT(tblOrders[[#This Row],[Order Date]],"mmm-yyyy") -> Mar-2026 | R102: =IF(N102="Cancelled",0,H102*INDEX(Assumptions!$C$7:$C$12,MATCH(F102,Assumptions!$B$7:$B$12,0))) -> 671.4942 | S102: =IF(N102="Cancelled",Assumptions!$C$19,IF(N102="Returned",Assumptions!$C$17+O102*Assumptions!$C$18+Assumptions!$C$20,Assumptions!$C$17+O102*Assumptions!$C$18)) -> 35.5 | T102: =R102+S102 -> 706.9942 | U102: =K102-T102 -> 116.8068 | V102: =IF(U102>0,U102,0) -> 116.8068 | W102: =IF(U102>0,U102/H102,0) -> 0.13568145 | X102: =IF(U102<0,-U102,0) -> 0 | Y102: =IF(U102<0,-U102/H102,0) -> 0 | Z102: =IF(U102>=0,"Profitable",IF(N102="Cancelled","Order Cancelled",IF(N102="Returned","Order Returned",IF(AND(I102>=0.15,U102<0),"High Discount",IF(S102>H102,"Delivery Cost Exceeded Order Value","Low Order Value / Thin Margin"))))) -> Profitable
A103: ORD10170 | B103: 46099.568 | C103: Karan Kapoor | D103: Chennai | E103: Mobile App | F103: Home & Living | G103: 3 | H103: 1230.3 | I103: 0.05 | J103: 0 | K103: =IF(N103="Cancelled",0,IF(N103="Returned",J103,H103*(1-I103)+J103)) -> 1168.785 | L103: Cash on Delivery | M103: Harpreet Singh | N103: Delivered | O103: 80 | P103: 5 | Q103: =TEXT(tblOrders[[#This Row],[Order Date]],"mmm-yyyy") -> Mar-2026 | R103: =IF(N103="Cancelled",0,H103*INDEX(Assumptions!$C$7:$C$12,MATCH(F103,Assumptions!$B$7:$B$12,0))) -> 799.695 | S103: =IF(N103="Cancelled",Assumptions!$C$19,IF(N103="Returned",Assumptions!$C$17+O103*Assumptions!$C$18+Assumptions!$C$20,Assumptions!$C$17+O103*Assumptions!$C$18)) -> 49 | T103: =R103+S103 -> 848.695 | U103: =K103-T103 -> 320.09 | V103: =IF(U103>0,U103,0) -> 320.09 | W103: =IF(U103>0,U103/H103,0) -> 0.26017232 | X103: =IF(U103<0,-U103,0) -> 0 | Y103: =IF(U103<0,-U103/H103,0) -> 0 | Z103: =IF(U103>=0,"Profitable",IF(N103="Cancelled","Order Cancelled",IF(N103="Returned","Order Returned",IF(AND(I103>=0.15,U103<0),"High Discount",IF(S103>H103,"Delivery Cost Exceeded Order Value","Low Order Value / Thin Margin"))))) -> Profitable
A104: ORD10184 | B104: 46099.876 | C104: Shreya Ghosh | D104: Mumbai | E104: Mobile App | F104: Fashion | G104: 1 | H104: 1924.56 | I104: 0 | J104: 0 | K104: =IF(N104="Cancelled",0,IF(N104="Returned",J104,H104*(1-I104)+J104)) -> 1924.56 | L104: Credit/Debit Card | M104: Lalita Rout | N104: Delivered | O104: 93 | P104: 5 | Q104: =TEXT(tblOrders[[#This Row],[Order Date]],"mmm-yyyy") -> Mar-2026 | R104: =IF(N104="Cancelled",0,H104*INDEX(Assumptions!$C$7:$C$12,MATCH(F104,Assumptions!$B$7:$B$12,0))) -> 1058.508 | S104: =IF(N104="Cancelled",Assumptions!$C$19,IF(N104="Returned",Assumptions!$C$17+O104*Assumptions!$C$18+Assumptions!$C$20,Assumptions!$C$17+O104*Assumptions!$C$18)) -> 52.9 | T104: =R104+S104 -> 1111.408 | U104: =K104-T104 -> 813.152 | V104: =IF(U104>0,U104,0) -> 813.152 | W104: =IF(U104>0,U104/H104,0) -> 0.4225132 | X104: =IF(U104<0,-U104,0) -> 0 | Y104: =IF(U104<0,-U104/H104,0) -> 0 | Z104: =IF(U104>=0,"Profitable",IF(N104="Cancelled","Order Cancelled",IF(N104="Returned","Order Returned",IF(AND(I104>=0.15,U104<0),"High Discount",IF(S104>H104,"Delivery Cost Exceeded Order Value","Low Order Value / Thin Margin"))))) -> Profitable
A105: ORD10115 | B105: 46099.882 | C105: Aarav Bose | D105: Delhi | E105: Website | F105: Food & Beverage | G105: 6 | H105: 239.27 | I105: 0 | J105: 39 | K105: =IF(N105="Cancelled",0,IF(N105="Returned",J105,H105*(1-I105)+J105)) -> 39 | L105: UPI/Wallet | M105: Pankaj Dey | N105: Returned | O105: 35 | P105: 1 | Q105: =TEXT(tblOrders[[#This Row],[Order Date]],"mmm-yyyy") -> Mar-2026 | R105: =IF(N105="Cancelled",0,H105*INDEX(Assumptions!$C$7:$C$12,MATCH(F105,Assumptions!$B$7:$B$12,0))) -> 107.6715 | S105: =IF(N105="Cancelled",Assumptions!$C$19,IF(N105="Returned",Assumptions!$C$17+O105*Assumptions!$C$18+Assumptions!$C$20,Assumptions!$C$17+O105*Assumptions!$C$18)) -> 55.5 | T105: =R105+S105 -> 163.1715 | U105: =K105-T105 -> -124.1715 | V105: =IF(U105>0,U105,0) -> 0 | W105: =IF(U105>0,U105/H105,0) -> 0 | X105: =IF(U105<0,-U105,0) -> 124.1715 | Y105: =IF(U105<0,-U105/H105,0) -> 0.51895975 | Z105: =IF(U105>=0,"Profitable",IF(N105="Cancelled","Order Cancelled",IF(N105="Returned","Order Returned",IF(AND(I105>=0.15,U105<0),"High Discount",IF(S105>H105,"Delivery Cost Exceeded Order Value","Low Order Value / Thin Margin"))))) -> Order Returned
A106: ORD10141 | B106: 46101.434 | C106: Ananya Nair | D106: Kolkata | E106: Website | F106: Food & Beverage | G106: 6 | H106: 715.87 | I106: 0.15 | J106: 29 | K106: =IF(N106="Cancelled",0,IF(N106="Returned",J106,H106*(1-I106)+J106)) -> 637.4895 | L106: Cash on Delivery | M106: Deepak Sahu | N106: Delivered | O106: 46 | P106: 3 | Q106: =TEXT(tblOrders[[#This Row],[Order Date]],"mmm-yyyy") -> Mar-2026 | R106: =IF(N106="Cancelled",0,H106*INDEX(Assumptions!$C$7:$C$12,MATCH(F106,Assumptions!$B$7:$B$12,0))) -> 322.1415 | S106: =IF(N106="Cancelled",Assumptions!$C$19,IF(N106="Returned",Assumptions!$C$17+O106*Assumptions!$C$18+Assumptions!$C$20,Assumptions!$C$17+O106*Assumptions!$C$18)) -> 38.8 | T106: =R106+S106 -> 360.9415 | U106: =K106-T106 -> 276.548 | V106: =IF(U106>0,U106,0) -> 276.548 | W106: =IF(U106>0,U106/H106,0) -> 0.38631036 | X106: =IF(U106<0,-U106,0) -> 0 | Y106: =IF(U106<0,-U106/H106,0) -> 0 | Z106: =IF(U106>=0,"Profitable",IF(N106="Cancelled","Order Cancelled",IF(N106="Returned","Order Returned",IF(AND(I106>=0.15,U106<0),"High Discount",IF(S106>H106,"Delivery Cost Exceeded Order Value","Low Order Value / Thin Margin"))))) -> Profitable
A107: ORD10048 | B107: 46101.735 | C107: Meera Pillai | D107: Pune | E107: Website | F107: Grocery | G107: 1 | H107: 1144.97 | I107: 0 | J107: 0 | K107: =IF(N107="Cancelled",0,IF(N107="Returned",J107,H107*(1-I107)+J107)) -> 1144.97 | L107: Credit/Debit Card | M107: Harpreet Singh | N107: Delivered | O107: 28 | P107: 3 | Q107: =TEXT(tblOrders[[#This Row],[Order Date]],"mmm-yyyy") -> Mar-2026 | R107: =IF(N107="Cancelled",0,H107*INDEX(Assumptions!$C$7:$C$12,MATCH(F107,Assumptions!$B$7:$B$12,0))) -> 893.0766 | S107: =IF(N107="Cancelled",Assumptions!$C$19,IF(N107="Returned",Assumptions!$C$17+O107*Assumptions!$C$18+Assumptions!$C$20,Assumptions!$C$17+O107*Assumptions!$C$18)) -> 33.4 | T107: =R107+S107 -> 926.4766 | U107: =K107-T107 -> 218.4934 | V107: =IF(U107>0,U107,0) -> 218.4934 | W107: =IF(U107>0,U107/H107,0) -> 0.19082893 | X107: =IF(U107<0,-U107,0) -> 0 | Y107: =IF(U107<0,-U107/H107,0) -> 0 | Z107: =IF(U107>=0,"Profitable",IF(N107="Cancelled","Order Cancelled",IF(N107="Returned","Order Returned",IF(AND(I107>=0.15,U107<0),"High Discount",IF(S107>H107,"Delivery Cost Exceeded Order Value","Low Order Value / Thin Margin"))))) -> Profitable
A108: ORD10043 | B108: 46101.776 | C108: Arjun Iyer | D108: Pune | E108: Mobile App | F108: Electronics | G108: 3 | H108: 6842.15 | I108: 0.15 | J108: 0 | K108: =IF(N108="Cancelled",0,IF(N108="Returned",J108,H108*(1-I108)+J108)) -> 5815.8275 | L108: Cash on Delivery | M108: Jyoti Panda | N108: Delivered | O108: 76 | P108: 4 | Q108: =TEXT(tblOrders[[#This Row],[Order Date]],"mmm-yyyy") -> Mar-2026 | R108: =IF(N108="Cancelled",0,H108*INDEX(Assumptions!$C$7:$C$12,MATCH(F108,Assumptions!$B$7:$B$12,0))) -> 6021.092 | S108: =IF(N108="Cancelled",Assumptions!$C$19,IF(N108="Returned",Assumptions!$C$17+O108*Assumptions!$C$18+Assumptions!$C$20,Assumptions!$C$17+O108*Assumptions!$C$18)) -> 47.8 | T108: =R108+S108 -> 6068.892 | U108: =K108-T108 -> -253.0645 | V108: =IF(U108>0,U108,0) -> 0 | W108: =IF(U108>0,U108/H108,0) -> 0 | X108: =IF(U108<0,-U108,0) -> 253.0645 | Y108: =IF(U108<0,-U108/H108,0) -> 0.036986108 | Z108: =IF(U108>=0,"Profitable",IF(N108="Cancelled","Order Cancelled",IF(N108="Returned","Order Returned",IF(AND(I108>=0.15,U108<0),"High Discount",IF(S108>H108,"Delivery Cost Exceeded Order Value","Low Order Value / Thin Margin"))))) -> High Discount
A109: ORD10037 | B109: 46102.401 | C109: Nikhil Iyer | D109: Pune | E109: Mobile App | F109: Grocery | G109: 6 | H109: 1103.43 | I109: 0.05 | J109: 0 | K109: =IF(N109="Cancelled",0,IF(N109="Returned",J109,H109*(1-I109)+J109)) -> 0 | L109: Net Banking | M109: Tarun Chauhan | N109: Returned | O109: 43 | P109: 1 | Q109: =TEXT(tblOrders[[#This Row],[Order Date]],"mmm-yyyy") -> Mar-2026 | R109: =IF(N109="Cancelled",0,H109*INDEX(Assumptions!$C$7:$C$12,MATCH(F109,Assumptions!$B$7:$B$12,0))) -> 860.6754 | S109: =IF(N109="Cancelled",Assumptions!$C$19,IF(N109="Returned",Assumptions!$C$17+O109*Assumptions!$C$18+Assumptions!$C$20,Assumptions!$C$17+O109*Assumptions!$C$18)) -> 57.9 | T109: =R109+S109 -> 918.5754 | U109: =K109-T109 -> -918.5754 | V109: =IF(U109>0,U109,0) -> 0 | W109: =IF(U109>0,U109/H109,0) -> 0 | X109: =IF(U109<0,-U109,0) -> 918.5754 | Y109: =IF(U109<0,-U109/H109,0) -> 0.83247274 | Z109: =IF(U109>=0,"Profitable",IF(N109="Cancelled","Order Cancelled",IF(N109="Returned","Order Returned",IF(AND(I109>=0.15,U109<0),"High Discount",IF(S109>H109,"Delivery Cost Exceeded Order Value","Low Order Value / Thin Margin"))))) -> Order Returned
A110: ORD10007 | B110: 46102.613 | C110: Manav Iyer | D110: Bhubaneswar | E110: Mobile App | F110: Food & Beverage | G110: 5 | H110: 461.19 | I110: 0 | J110: 39 | K110: =IF(N110="Cancelled",0,IF(N110="Returned",J110,H110*(1-I110)+J110)) -> 500.19 | L110: UPI/Wallet | M110: Harpreet Singh | N110: Delivered | O110: 93 | P110: 5 | Q110: =TEXT(tblOrders[[#This Row],[Order Date]],"mmm-yyyy") -> Mar-2026 | R110: =IF(N110="Cancelled",0,H110*INDEX(Assumptions!$C$7:$C$12,MATCH(F110,Assumptions!$B$7:$B$12,0))) -> 207.5355 | S110: =IF(N110="Cancelled",Assumptions!$C$19,IF(N110="Returned",Assumptions!$C$17+O110*Assumptions!$C$18+Assumptions!$C$20,Assumptions!$C$17+O110*Assumptions!$C$18)) -> 52.9 | T110: =R110+S110 -> 260.4355 | U110: =K110-T110 -> 239.7545 | V110: =IF(U110>0,U110,0) -> 239.7545 | W110: =IF(U110>0,U110/H110,0) -> 0.51986058 | X110: =IF(U110<0,-U110,0) -> 0 | Y110: =IF(U110<0,-U110/H110,0) -> 0 | Z110: =IF(U110>=0,"Profitable",IF(N110="Cancelled","Order Cancelled",IF(N110="Returned","Order Returned",IF(AND(I110>=0.15,U110<0),"High Discount",IF(S110>H110,"Delivery Cost Exceeded Order Value","Low Order Value / Thin Margin"))))) -> Profitable
A111: ORD10200 | B111: 46102.783 | C111: Kritika Mishra | D111: Bengaluru | E111: Mobile App | F111: Food & Beverage | G111: 1 | H111: 666.32 | I111: 0.15 | J111: 29 | K111: =IF(N111="Cancelled",0,IF(N111="Returned",J111,H111*(1-I111)+J111)) -> 595.372 | L111: Credit/Debit Card | M111: Rekha Sethi | N111: Delivered | O111: 62 | P111: 5 | Q111: =TEXT(tblOrders[[#This Row],[Order Date]],"mmm-yyyy") -> Mar-2026 | R111: =IF(N111="Cancelled",0,H111*INDEX(Assumptions!$C$7:$C$12,MATCH(F111,Assumptions!$B$7:$B$12,0))) -> 299.844 | S111: =IF(N111="Cancelled",Assumptions!$C$19,IF(N111="Returned",Assumptions!$C$17+O111*Assumptions!$C$18+Assumptions!$C$20,Assumptions!$C$17+O111*Assumptions!$C$18)) -> 43.6 | T111: =R111+S111 -> 343.444 | U111: =K111-T111 -> 251.928 | V111: =IF(U111>0,U111,0) -> 251.928 | W111: =IF(U111>0,U111/H111,0) -> 0.37808861 | X111: =IF(U111<0,-U111,0) -> 0 | Y111: =IF(U111<0,-U111/H111,0) -> 0 | Z111: =IF(U111>=0,"Profitable",IF(N111="Cancelled","Order Cancelled",IF(N111="Returned","Order Returned",IF(AND(I111>=0.15,U111<0),"High Discount",IF(S111>H111,"Delivery Cost Exceeded Order Value","Low Order Value / Thin Margin"))))) -> Profitable
A112: ORD10059 | B112: 46104.812 | C112: Karan Reddy | D112: Kolkata | E112: Website | F112: Food & Beverage | G112: 4 | H112: 890.73 | I112: 0.2 | J112: 39 | K112: =IF(N112="Cancelled",0,IF(N112="Returned",J112,H112*(1-I112)+J112)) -> 39 | L112: Net Banking | M112: Tarun Chauhan | N112: Returned | O112: 34 | P112: 3 | Q112: =TEXT(tblOrders[[#This Row],[Order Date]],"mmm-yyyy") -> Mar-2026 | R112: =IF(N112="Cancelled",0,H112*INDEX(Assumptions!$C$7:$C$12,MATCH(F112,Assumptions!$B$7:$B$12,0))) -> 400.8285 | S112: =IF(N112="Cancelled",Assumptions!$C$19,IF(N112="Returned",Assumptions!$C$17+O112*Assumptions!$C$18+Assumptions!$C$20,Assumptions!$C$17+O112*Assumptions!$C$18)) -> 55.2 | T112: =R112+S112 -> 456.0285 | U112: =K112-T112 -> -417.0285 | V112: =IF(U112>0,U112,0) -> 0 | W112: =IF(U112>0,U112/H112,0) -> 0 | X112: =IF(U112<0,-U112,0) -> 417.0285 | Y112: =IF(U112<0,-U112/H112,0) -> 0.46818733 | Z112: =IF(U112>=0,"Profitable",IF(N112="Cancelled","Order Cancelled",IF(N112="Returned","Order Returned",IF(AND(I112>=0.15,U112<0),"High Discount",IF(S112>H112,"Delivery Cost Exceeded Order Value","Low Order Value / Thin Margin"))))) -> Order Returned
... A137: ORD10137 | B137: 46124.855 | C137: Rahul Pillai | D137: Kolkata | E137: Website | F137: Grocery | G137: 3 | H137: 1070.58 | I137: 0 | J137: 0 | K137: =IF(N137="Cancelled",0,IF(N137="Returned",J137,H137*(1-I137)+J137)) -> 1070.58 | L137: Cash on Delivery | M137: Jyoti Panda | N137: Delivered | O137: 31 | P137: 4 | Q137: =TEXT(tblOrders[[#This Row],[Order Date]],"mmm-yyyy") -> Apr-2026 | R137: =IF(N137="Cancelled",0,H137*INDEX(Assumptions!$C$7:$C$12,MATCH(F137,Assumptions!$B$7:$B$12,0))) -> 835.0524 | S137: =IF(N137="Cancelled",Assumptions!$C$19,IF(N137="Returned",Assumptions!$C$17+O137*Assumptions!$C$18+Assumptions!$C$20,Assumptions!$C$17+O137*Assumptions!$C$18)) -> 34.3 | T137: =R137+S137 -> 869.3524 | U137: =K137-T137 -> 201.2276 | V137: =IF(U137>0,U137,0) -> 201.2276 | W137: =IF(U137>0,U137/H137,0) -> 0.18796129 | X137: =IF(U137<0,-U137,0) -> 0 | Y137: =IF(U137<0,-U137/H137,0) -> 0 | Z137: =IF(U137>=0,"Profitable",IF(N137="Cancelled","Order Cancelled",IF(N137="Returned","Order Returned",IF(AND(I137>=0.15,U137<0),"High Discount",IF(S137>H137,"Delivery Cost Exceeded Order Value","Low Order Value / Thin Margin"))))) -> Profitable
A138: ORD10133 | B138: 46124.89 | C138: Simran Menon | D138: Hyderabad | E138: Website | F138: Home & Living | G138: 3 | H138: 443.99 | I138: 0.15 | J138: 29 | K138: =IF(N138="Cancelled",0,IF(N138="Returned",J138,H138*(1-I138)+J138)) -> 0 | L138: Cash on Delivery | M138: Imran Khan | N138: Cancelled | Q138: =TEXT(tblOrders[[#This Row],[Order Date]],"mmm-yyyy") -> Apr-2026 | R138: =IF(N138="Cancelled",0,H138*INDEX(Assumptions!$C$7:$C$12,MATCH(F138,Assumptions!$B$7:$B$12,0))) -> 0 | S138: =IF(N138="Cancelled",Assumptions!$C$19,IF(N138="Returned",Assumptions!$C$17+O138*Assumptions!$C$18+Assumptions!$C$20,Assumptions!$C$17+O138*Assumptions!$C$18)) -> 15 | T138: =R138+S138 -> 15 | U138: =K138-T138 -> -15 | V138: =IF(U138>0,U138,0) -> 0 | W138: =IF(U138>0,U138/H138,0) -> 0 | X138: =IF(U138<0,-U138,0) -> 15 | Y138: =IF(U138<0,-U138/H138,0) -> 0.033784545 | Z138: =IF(U138>=0,"Profitable",IF(N138="Cancelled","Order Cancelled",IF(N138="Returned","Order Returned",IF(AND(I138>=0.15,U138<0),"High Discount",IF(S138>H138,"Delivery Cost Exceeded Order Value","Low Order Value / Thin Margin"))))) -> Order Cancelled
...

Sheet Assumptions
B2: Cost Model Assumptions — PLACEHOLDER VALUES, replace with your real cost data
B3: Every Profit/Loss figure in this workbook is driven from the cells below. Edit only the yellow cells.
B5: Cost of Goods Sold (COGS) — % of Order Value, by Category
B6: Category | C6: COGS % of Order Value
B7: Grocery | C7: 0.78
B8: Electronics | C8: 0.88
B9: Fashion | C9: 0.55
B10: Food & Beverage | C10: 0.45
B11: Pharmacy | C11: 0.7
B12: Home & Living | C12: 0.65
B15: Delivery / Fulfillment Cost Drivers
B16: Cost Driver | C16: Value | D16: Notes
B17: Base delivery cost per order ($) | C17: 25 | D17: Rider pickup + base fuel/vehicle cost per dispatched order
B18: Delivery cost per minute in transit ($) | C18: 0.3 | D18: Marginal fuel/time cost per minute of delivery time
B19: Cancelled-order dispatch cost ($) | C19: 15 | D19: Sunk cost when an order is cancelled after dispatch begins
B20: Returned-order reverse logistics cost ($) | C20: 20 | D20: Extra pickup + restocking cost on top of base delivery cost
